[{"closedIssues":113972,"openIssues":6020,"timestamp":1631858605,"closedPRs":2597,"stars":121457,"openPRs":246,"mergedPRs":7483},{"timestamp":1631854974,"openIssues":6017,"openPRs":246,"closedPRs":2597,"stars":121455,"closedIssues":113972,"mergedPRs":7483},{"closedPRs":2597,"timestamp":1631851433,"mergedPRs":7483,"closedIssues":113969,"stars":121453,"openIssues":6019,"openPRs":245},{"mergedPRs":7483,"closedIssues":113967,"timestamp":1631847779,"closedPRs":2597,"stars":121452,"openIssues":6020,"openPRs":245},{"stars":121448,"openPRs":245,"closedIssues":113966,"openIssues":6021,"mergedPRs":7483,"closedPRs":2597,"timestamp":1631844961},{"openPRs":246,"mergedPRs":7482,"stars":121445,"openIssues":6027,"closedIssues":113960,"closedPRs":2597,"timestamp":1631841978},{"timestamp":1631837075,"closedIssues":113957,"openIssues":6023,"closedPRs":2597,"openPRs":246,"stars":121441,"mergedPRs":7482},{"openPRs":246,"closedPRs":2597,"stars":121441,"mergedPRs":7481,"closedIssues":113954,"timestamp":1631833378,"openIssues":6024},{"openIssues":6027,"openPRs":246,"timestamp":1631829802,"closedPRs":2597,"mergedPRs":7481,"stars":121440,"closedIssues":113951},{"closedIssues":113951,"openIssues":6024,"openPRs":246,"stars":121441,"timestamp":1631826173,"mergedPRs":7481,"closedPRs":2597},{"openIssues":6020,"closedIssues":113951,"closedPRs":2597,"stars":121438,"timestamp":1631822580,"openPRs":246,"mergedPRs":7481},{"openIssues":6016,"closedIssues":113950,"closedPRs":2597,"openPRs":245,"stars":121437,"timestamp":1631818974,"mergedPRs":7480},{"openPRs":246,"closedIssues":113946,"mergedPRs":7479,"closedPRs":2597,"stars":121434,"timestamp":1631815406,"openIssues":6018},{"openPRs":246,"closedIssues":113940,"closedPRs":2597,"timestamp":1631811964,"mergedPRs":7479,"stars":121436,"openIssues":6019},{"timestamp":1631808202,"openPRs":249,"mergedPRs":7476,"openIssues":6019,"stars":121435,"closedPRs":2597,"closedIssues":113935},{"openPRs":249,"openIssues":6024,"closedIssues":113929,"mergedPRs":7476,"timestamp":1631804592,"stars":121432,"closedPRs":2597},{"closedIssues":113922,"timestamp":1631800983,"closedPRs":2597,"stars":121433,"openIssues":6026,"mergedPRs":7476,"openPRs":249},{"stars":121429,"closedPRs":2597,"timestamp":1631797669,"mergedPRs":7476,"openIssues":6026,"closedIssues":113920,"openPRs":249},{"closedPRs":2597,"openIssues":6024,"openPRs":250,"timestamp":1631793817,"closedIssues":113919,"stars":121426,"mergedPRs":7475},{"stars":121421,"timestamp":1631790185,"closedPRs":2597,"closedIssues":113917,"openPRs":251,"mergedPRs":7474,"openIssues":6021},{"closedIssues":113915,"stars":121422,"openPRs":251,"openIssues":6018,"timestamp":1631786587,"closedPRs":2597,"mergedPRs":7474},{"openIssues":6015,"openPRs":253,"timestamp":1631783564,"stars":121424,"closedPRs":2597,"closedIssues":113913,"mergedPRs":7472},{"openPRs":250,"stars":121423,"closedIssues":113909,"closedPRs":2597,"mergedPRs":7472,"timestamp":1631779708,"openIssues":6009},{"mergedPRs":7472,"timestamp":1631775786,"closedIssues":113908,"closedPRs":2597,"stars":121423,"openPRs":250,"openIssues":6007},{"timestamp":1631772209,"closedPRs":2597,"openPRs":250,"closedIssues":113907,"mergedPRs":7472,"stars":121422,"openIssues":6005},{"openIssues":6006,"closedIssues":113906,"mergedPRs":7472,"openPRs":250,"stars":121421,"timestamp":1631768571,"closedPRs":2597},{"openPRs":250,"closedPRs":2597,"openIssues":6005,"closedIssues":113906,"timestamp":1631764997,"mergedPRs":7472,"stars":121419},{"closedPRs":2597,"closedIssues":113906,"stars":121419,"openPRs":250,"openIssues":6000,"mergedPRs":7472,"timestamp":1631761373},{"openPRs":250,"openIssues":5999,"closedIssues":113906,"mergedPRs":7472,"stars":121418,"closedPRs":2597,"timestamp":1631758548},{"closedIssues":113906,"openPRs":250,"closedPRs":2597,"mergedPRs":7472,"stars":121416,"openIssues":5997,"timestamp":1631755524},{"openIssues":5995,"mergedPRs":7471,"openPRs":250,"closedPRs":2597,"timestamp":1631750703,"stars":121415,"closedIssues":113904},{"timestamp":1631746980,"openIssues":6002,"closedPRs":2597,"closedIssues":113897,"mergedPRs":7471,"stars":121414,"openPRs":249},{"mergedPRs":7471,"timestamp":1631743381,"stars":121413,"closedPRs":2597,"closedIssues":113892,"openPRs":249,"openIssues":6008},{"closedIssues":113881,"openIssues":6019,"mergedPRs":7469,"closedPRs":2596,"timestamp":1631739808,"stars":121408,"openPRs":249},{"timestamp":1631736185,"closedIssues":113877,"openIssues":6022,"openPRs":250,"mergedPRs":7468,"stars":121407,"closedPRs":2596},{"timestamp":1631732594,"closedIssues":113874,"closedPRs":2596,"openIssues":6023,"stars":121406,"openPRs":250,"mergedPRs":7468},{"closedPRs":2596,"timestamp":1631728996,"closedIssues":113874,"mergedPRs":7468,"openPRs":250,"openIssues":6021,"stars":121403},{"timestamp":1631725516,"stars":121401,"openIssues":6018,"mergedPRs":7468,"closedIssues":113874,"openPRs":250,"closedPRs":2596},{"openIssues":6016,"openPRs":249,"closedPRs":2596,"stars":121397,"mergedPRs":7468,"timestamp":1631721779,"closedIssues":113872},{"mergedPRs":7468,"openPRs":249,"stars":121393,"openIssues":6011,"timestamp":1631718182,"closedPRs":2596,"closedIssues":113872},{"openPRs":249,"closedIssues":113867,"stars":121391,"timestamp":1631714589,"mergedPRs":7468,"closedPRs":2596,"openIssues":6010},{"openIssues":6009,"mergedPRs":7468,"timestamp":1631711248,"closedPRs":2596,"stars":121386,"openPRs":249,"closedIssues":113867},{"openIssues":6006,"mergedPRs":7468,"stars":121383,"openPRs":249,"timestamp":1631707388,"closedIssues":113864,"closedPRs":2595},{"mergedPRs":7468,"closedIssues":113843,"openIssues":6021,"stars":121382,"openPRs":248,"closedPRs":2595,"timestamp":1631703774},{"stars":121382,"closedPRs":2595,"closedIssues":113841,"mergedPRs":7468,"openPRs":248,"openIssues":6023,"timestamp":1631700184},{"timestamp":1631696585,"closedPRs":2595,"openPRs":248,"mergedPRs":7467,"stars":121379,"closedIssues":113838,"openIssues":6025},{"closedPRs":2595,"closedIssues":113836,"openIssues":6023,"stars":121381,"timestamp":1631693003,"openPRs":248,"mergedPRs":7467},{"closedPRs":2595,"closedIssues":113835,"timestamp":1631689394,"stars":121380,"openPRs":248,"openIssues":6024,"mergedPRs":7467},{"mergedPRs":7467,"openPRs":248,"closedPRs":2595,"timestamp":1631685802,"closedIssues":113832,"openIssues":6024,"stars":121377},{"closedIssues":113825,"timestamp":1631682166,"closedPRs":2595,"mergedPRs":7466,"openIssues":6030,"openPRs":249,"stars":121374},{"openPRs":249,"closedPRs":2595,"stars":121369,"closedIssues":113812,"mergedPRs":7466,"timestamp":1631678598,"openIssues":6043},{"closedIssues":113812,"closedPRs":2595,"timestamp":1631674987,"mergedPRs":7466,"openPRs":249,"openIssues":6043,"stars":121364},{"openPRs":249,"stars":121361,"timestamp":1631671944,"closedIssues":113812,"closedPRs":2595,"mergedPRs":7466,"openIssues":6039},{"stars":121358,"closedPRs":2595,"mergedPRs":7466,"openPRs":249,"closedIssues":113809,"timestamp":1631669052,"openIssues":6041},{"openIssues":6039,"closedIssues":113810,"stars":121358,"openPRs":249,"timestamp":1631664297,"mergedPRs":7466,"closedPRs":2595},{"timestamp":1631660577,"openPRs":249,"closedPRs":2595,"mergedPRs":7466,"stars":121355,"closedIssues":113806,"openIssues":6041},{"openIssues":6042,"openPRs":249,"stars":121354,"mergedPRs":7466,"closedPRs":2595,"closedIssues":113803,"timestamp":1631656998},{"timestamp":1631653390,"openIssues":6041,"openPRs":250,"closedIssues":113802,"stars":121354,"closedPRs":2595,"mergedPRs":7465},{"mergedPRs":7465,"timestamp":1631649807,"stars":121350,"closedIssues":113800,"openPRs":250,"openIssues":6041,"closedPRs":2595},{"openIssues":6044,"closedIssues":113793,"closedPRs":2594,"openPRs":251,"mergedPRs":7465,"timestamp":1631646189,"stars":121350},{"openPRs":250,"mergedPRs":7465,"timestamp":1631642575,"stars":121347,"openIssues":6047,"closedPRs":2594,"closedIssues":113788},{"openPRs":250,"mergedPRs":7465,"stars":121343,"timestamp":1631639210,"closedPRs":2594,"openIssues":6048,"closedIssues":113783},{"closedPRs":2594,"closedIssues":113774,"timestamp":1631635396,"openPRs":252,"openIssues":6047,"stars":121342,"mergedPRs":7463},{"openPRs":254,"openIssues":6049,"closedIssues":113770,"timestamp":1631631778,"closedPRs":2594,"mergedPRs":7461,"stars":121340},{"closedPRs":2594,"openIssues":6049,"timestamp":1631628185,"stars":121335,"mergedPRs":7460,"openPRs":255,"closedIssues":113767},{"closedPRs":2594,"stars":121334,"openIssues":6051,"openPRs":256,"timestamp":1631624840,"closedIssues":113763,"mergedPRs":7459},{"closedIssues":113763,"openPRs":256,"closedPRs":2594,"stars":121330,"openIssues":6047,"timestamp":1631620987,"mergedPRs":7459},{"stars":121325,"openIssues":6055,"closedIssues":113752,"mergedPRs":7459,"timestamp":1631617376,"openPRs":256,"closedPRs":2594},{"timestamp":1631613790,"openIssues":6051,"closedIssues":113751,"closedPRs":2594,"stars":121325,"openPRs":256,"mergedPRs":7459},{"openPRs":256,"closedPRs":2594,"openIssues":6052,"timestamp":1631610184,"closedIssues":113749,"mergedPRs":7459,"stars":121322},{"openIssues":6050,"mergedPRs":7457,"stars":121317,"openPRs":257,"closedIssues":113744,"timestamp":1631606614,"closedPRs":2594},{"closedIssues":113738,"closedPRs":2594,"mergedPRs":7457,"stars":121315,"timestamp":1631602984,"openPRs":257,"openIssues":6055},{"mergedPRs":7457,"openPRs":257,"closedPRs":2594,"stars":121311,"openIssues":6057,"timestamp":1631599866,"closedIssues":113735},{"openPRs":257,"stars":121307,"openIssues":6055,"closedPRs":2594,"closedIssues":113735,"mergedPRs":7457,"timestamp":1631595771},{"openPRs":257,"stars":121303,"mergedPRs":7457,"openIssues":6050,"closedPRs":2594,"timestamp":1631592178,"closedIssues":113734},{"closedPRs":2594,"openIssues":6046,"openPRs":257,"closedIssues":113734,"stars":121302,"timestamp":1631588585,"mergedPRs":7457},{"timestamp":1631585566,"closedPRs":2594,"stars":121297,"openPRs":256,"closedIssues":113734,"mergedPRs":7457,"openIssues":6044},{"closedIssues":113734,"closedPRs":2594,"timestamp":1631582680,"stars":121295,"openIssues":6042,"openPRs":256,"mergedPRs":7457},{"openPRs":255,"mergedPRs":7457,"stars":121294,"openIssues":6041,"closedPRs":2594,"timestamp":1631577912,"closedIssues":113734},{"timestamp":1631574195,"stars":121294,"openPRs":256,"closedIssues":113731,"mergedPRs":7456,"closedPRs":2594,"openIssues":6043},{"closedIssues":113725,"openPRs":258,"openIssues":6047,"stars":121295,"closedPRs":2594,"mergedPRs":7454,"timestamp":1631570584},{"openIssues":6048,"openPRs":257,"closedIssues":113721,"mergedPRs":7454,"timestamp":1631566974,"stars":121295,"closedPRs":2594},{"closedPRs":2594,"mergedPRs":7454,"stars":121295,"openIssues":6044,"openPRs":257,"closedIssues":113719,"timestamp":1631563402},{"closedIssues":113713,"closedPRs":2593,"mergedPRs":7454,"openPRs":257,"openIssues":6044,"timestamp":1631559783,"stars":121294},{"closedPRs":2593,"closedIssues":113707,"openIssues":6050,"openPRs":256,"stars":121291,"mergedPRs":7454,"timestamp":1631556255},{"mergedPRs":7454,"stars":121287,"openPRs":256,"openIssues":6049,"timestamp":1631552842,"closedPRs":2593,"closedIssues":113702},{"closedIssues":113701,"mergedPRs":7453,"openPRs":255,"stars":121286,"closedPRs":2593,"timestamp":1631548987,"openIssues":6043},{"closedIssues":113697,"mergedPRs":7453,"timestamp":1631545389,"closedPRs":2593,"openIssues":6041,"stars":121286,"openPRs":255},{"openIssues":6047,"timestamp":1631541781,"closedPRs":2593,"stars":121280,"closedIssues":113689,"mergedPRs":7453,"openPRs":254},{"closedPRs":2593,"openPRs":255,"closedIssues":113682,"openIssues":6049,"timestamp":1631538558,"mergedPRs":7452,"stars":121278},{"openIssues":6047,"openPRs":255,"stars":121275,"timestamp":1631534583,"closedPRs":2593,"closedIssues":113679,"mergedPRs":7452},{"timestamp":1631530985,"closedIssues":113676,"mergedPRs":7452,"openPRs":255,"stars":121272,"closedPRs":2593,"openIssues":6047},{"stars":121271,"mergedPRs":7452,"openIssues":6046,"closedPRs":2593,"closedIssues":113674,"openPRs":255,"timestamp":1631527395},{"openPRs":255,"openIssues":6050,"mergedPRs":7452,"closedPRs":2593,"timestamp":1631523788,"stars":121267,"closedIssues":113667},{"openPRs":255,"closedPRs":2593,"openIssues":6049,"closedIssues":113666,"mergedPRs":7452,"stars":121263,"timestamp":1631520199},{"openIssues":6050,"closedIssues":113663,"closedPRs":2593,"openPRs":255,"stars":121263,"timestamp":1631516594,"mergedPRs":7452},{"mergedPRs":7452,"closedPRs":2593,"openPRs":255,"stars":121261,"openIssues":6052,"closedIssues":113661,"timestamp":1631513011},{"openIssues":6048,"stars":121258,"closedPRs":2593,"mergedPRs":7452,"openPRs":252,"closedIssues":113661,"timestamp":1631509387},{"timestamp":1631505800,"closedPRs":2593,"mergedPRs":7452,"stars":121257,"closedIssues":113661,"openPRs":252,"openIssues":6048},{"closedPRs":2593,"openIssues":6048,"mergedPRs":7452,"openPRs":252,"closedIssues":113660,"timestamp":1631502191,"stars":121256},{"closedIssues":113660,"openPRs":252,"mergedPRs":7452,"timestamp":1631499182,"openIssues":6048,"closedPRs":2593,"stars":121254},{"closedIssues":113661,"mergedPRs":7452,"closedPRs":2593,"stars":121255,"openIssues":6045,"timestamp":1631496267,"openPRs":252},{"openIssues":6047,"openPRs":252,"closedIssues":113659,"closedPRs":2593,"timestamp":1631491493,"stars":121255,"mergedPRs":7452},{"timestamp":1631487768,"closedIssues":113659,"stars":121255,"closedPRs":2593,"mergedPRs":7452,"openPRs":252,"openIssues":6047},{"timestamp":1631484175,"closedPRs":2593,"mergedPRs":7452,"stars":121255,"closedIssues":113659,"openIssues":6046,"openPRs":252},{"openIssues":6046,"closedIssues":113659,"closedPRs":2593,"stars":121253,"timestamp":1631480576,"mergedPRs":7452,"openPRs":252},{"openPRs":252,"closedIssues":113659,"stars":121251,"timestamp":1631477004,"closedPRs":2593,"openIssues":6046,"mergedPRs":7452},{"closedIssues":113659,"mergedPRs":7452,"timestamp":1631473388,"openPRs":252,"openIssues":6046,"closedPRs":2593,"stars":121249},{"closedPRs":2593,"stars":121249,"closedIssues":113659,"openPRs":252,"mergedPRs":7452,"timestamp":1631469807,"openIssues":6044},{"openPRs":252,"timestamp":1631466366,"openIssues":6043,"closedIssues":113659,"mergedPRs":7452,"stars":121248,"closedPRs":2593},{"openIssues":6041,"openPRs":252,"closedIssues":113659,"closedPRs":2593,"timestamp":1631462580,"mergedPRs":7452,"stars":121247},{"openPRs":252,"mergedPRs":7452,"closedPRs":2593,"closedIssues":113659,"timestamp":1631458981,"openIssues":6039,"stars":121242},{"timestamp":1631455386,"stars":121243,"mergedPRs":7452,"closedPRs":2593,"openIssues":6038,"openPRs":251,"closedIssues":113659},{"closedPRs":2593,"mergedPRs":7452,"closedIssues":113659,"openIssues":6036,"stars":121242,"timestamp":1631451989,"openPRs":251},{"openPRs":251,"mergedPRs":7452,"stars":121242,"timestamp":1631448198,"openIssues":6034,"closedIssues":113659,"closedPRs":2593},{"timestamp":1631444589,"openIssues":6032,"openPRs":251,"closedPRs":2593,"mergedPRs":7452,"closedIssues":113659,"stars":121241},{"timestamp":1631440996,"stars":121239,"closedPRs":2593,"openPRs":251,"mergedPRs":7452,"openIssues":6032,"closedIssues":113659},{"mergedPRs":7452,"openIssues":6031,"closedPRs":2593,"closedIssues":113659,"timestamp":1631437398,"stars":121239,"openPRs":251},{"closedPRs":2593,"mergedPRs":7452,"openPRs":251,"stars":121237,"openIssues":6031,"closedIssues":113659,"timestamp":1631433794},{"closedPRs":2593,"openIssues":6031,"timestamp":1631430176,"stars":121233,"mergedPRs":7452,"openPRs":251,"closedIssues":113659},{"stars":121231,"closedIssues":113659,"mergedPRs":7452,"openIssues":6028,"closedPRs":2593,"openPRs":251,"timestamp":1631426584},{"closedPRs":2593,"mergedPRs":7452,"closedIssues":113659,"timestamp":1631423173,"openPRs":251,"openIssues":6028,"stars":121229},{"openPRs":251,"stars":121228,"closedIssues":113659,"timestamp":1631419378,"closedPRs":2593,"openIssues":6027,"mergedPRs":7452},{"closedPRs":2593,"stars":121226,"timestamp":1631415791,"mergedPRs":7452,"closedIssues":113659,"openIssues":6027,"openPRs":251},{"timestamp":1631412836,"openIssues":6026,"openPRs":251,"closedIssues":113659,"stars":121224,"mergedPRs":7452,"closedPRs":2593},{"mergedPRs":7452,"openPRs":251,"timestamp":1631409913,"openIssues":6025,"closedIssues":113659,"stars":121223,"closedPRs":2593},{"closedPRs":2593,"openPRs":251,"openIssues":6023,"mergedPRs":7452,"closedIssues":113659,"timestamp":1631405117,"stars":121223},{"stars":121222,"mergedPRs":7452,"openPRs":251,"timestamp":1631401381,"closedPRs":2593,"openIssues":6023,"closedIssues":113659},{"timestamp":1631397778,"closedPRs":2593,"closedIssues":113658,"openIssues":6023,"stars":121221,"openPRs":251,"mergedPRs":7452},{"closedPRs":2593,"openPRs":251,"stars":121220,"timestamp":1631394229,"mergedPRs":7452,"closedIssues":113658,"openIssues":6022},{"openIssues":6022,"closedPRs":2593,"closedIssues":113657,"mergedPRs":7452,"openPRs":250,"stars":121218,"timestamp":1631390575},{"stars":121217,"timestamp":1631386984,"mergedPRs":7452,"closedPRs":2593,"openIssues":6020,"openPRs":250,"closedIssues":113657},{"stars":121216,"openIssues":6019,"mergedPRs":7452,"closedIssues":113656,"timestamp":1631383398,"closedPRs":2593,"openPRs":250},{"closedPRs":2593,"mergedPRs":7452,"openIssues":6019,"timestamp":1631379957,"openPRs":250,"closedIssues":113655,"stars":121215},{"stars":121213,"openPRs":250,"mergedPRs":7452,"timestamp":1631376250,"closedPRs":2593,"openIssues":6017,"closedIssues":113655},{"stars":121211,"mergedPRs":7452,"closedIssues":113655,"openPRs":250,"openIssues":6016,"timestamp":1631372585,"closedPRs":2593},{"closedIssues":113655,"timestamp":1631368989,"closedPRs":2593,"openPRs":250,"openIssues":6015,"stars":121210,"mergedPRs":7452},{"stars":121211,"openIssues":6012,"timestamp":1631365578,"closedPRs":2593,"mergedPRs":7452,"closedIssues":113655,"openPRs":250},{"mergedPRs":7452,"closedIssues":113654,"openIssues":6012,"timestamp":1631361811,"stars":121210,"openPRs":250,"closedPRs":2593},{"mergedPRs":7452,"closedPRs":2593,"stars":121209,"openIssues":6012,"openPRs":250,"timestamp":1631358202,"closedIssues":113654},{"timestamp":1631354585,"closedIssues":113654,"closedPRs":2593,"openPRs":250,"mergedPRs":7452,"stars":121207,"openIssues":6011},{"mergedPRs":7452,"openPRs":250,"stars":121206,"openIssues":6009,"timestamp":1631350987,"closedIssues":113654,"closedPRs":2593},{"timestamp":1631347416,"closedIssues":113653,"openPRs":251,"closedPRs":2593,"mergedPRs":7451,"stars":121207,"openIssues":6010},{"timestamp":1631343784,"closedIssues":113653,"stars":121205,"mergedPRs":7451,"openPRs":251,"openIssues":6008,"closedPRs":2593},{"closedIssues":113652,"timestamp":1631340198,"mergedPRs":7451,"openIssues":6005,"openPRs":251,"closedPRs":2593,"stars":121204},{"mergedPRs":7451,"timestamp":1631336567,"closedIssues":113652,"stars":121202,"openIssues":6004,"openPRs":249,"closedPRs":2593},{"closedPRs":2593,"stars":121202,"closedIssues":113652,"mergedPRs":7451,"timestamp":1631332969,"openIssues":6002,"openPRs":249},{"openIssues":6002,"closedIssues":113651,"closedPRs":2593,"timestamp":1631329370,"openPRs":249,"stars":121203,"mergedPRs":7451},{"closedPRs":2593,"mergedPRs":7451,"closedIssues":113645,"stars":121202,"openIssues":6007,"timestamp":1631326369,"openPRs":249},{"closedIssues":113645,"openPRs":249,"stars":121199,"timestamp":1631323387,"mergedPRs":7451,"openIssues":6007,"closedPRs":2593},{"openPRs":249,"closedIssues":113645,"stars":121198,"openIssues":6006,"closedPRs":2593,"mergedPRs":7451,"timestamp":1631318691},{"timestamp":1631314993,"closedIssues":113644,"openIssues":6006,"stars":121196,"mergedPRs":7451,"openPRs":249,"closedPRs":2593},{"stars":121195,"timestamp":1631311402,"mergedPRs":7451,"closedPRs":2593,"openPRs":249,"closedIssues":113644,"openIssues":6005},{"openPRs":249,"mergedPRs":7450,"timestamp":1631307794,"closedIssues":113644,"openIssues":6003,"closedPRs":2593,"stars":121195},{"closedIssues":113640,"openPRs":249,"stars":121193,"openIssues":6004,"mergedPRs":7450,"timestamp":1631304179,"closedPRs":2593},{"timestamp":1631300562,"openIssues":6002,"closedIssues":113640,"mergedPRs":7450,"stars":121193,"openPRs":249,"closedPRs":2593},{"closedPRs":2593,"closedIssues":113637,"timestamp":1631297020,"stars":121190,"openIssues":5998,"mergedPRs":7450,"openPRs":248},{"closedPRs":2593,"openIssues":5998,"mergedPRs":7450,"stars":121190,"closedIssues":113635,"openPRs":248,"timestamp":1631293513},{"openIssues":5998,"closedPRs":2593,"stars":121189,"openPRs":250,"closedIssues":113632,"mergedPRs":7448,"timestamp":1631289803},{"timestamp":1631286194,"closedIssues":113631,"stars":121187,"closedPRs":2592,"mergedPRs":7446,"openPRs":251,"openIssues":5996},{"closedIssues":113632,"mergedPRs":7446,"timestamp":1631282593,"closedPRs":2592,"openPRs":250,"stars":121186,"openIssues":5994},{"closedPRs":2592,"openPRs":249,"timestamp":1631279241,"mergedPRs":7446,"stars":121182,"openIssues":5997,"closedIssues":113628},{"openIssues":5995,"stars":121181,"timestamp":1631275400,"openPRs":248,"closedPRs":2592,"mergedPRs":7446,"closedIssues":113626},{"openPRs":248,"closedIssues":113608,"timestamp":1631271797,"closedPRs":2592,"mergedPRs":7446,"openIssues":6010,"stars":121176},{"timestamp":1631268238,"openPRs":249,"stars":121176,"closedIssues":113607,"openIssues":6009,"closedPRs":2591,"mergedPRs":7446},{"closedPRs":2591,"openPRs":248,"mergedPRs":7446,"timestamp":1631264642,"stars":121175,"openIssues":6006,"closedIssues":113608},{"closedIssues":113604,"stars":121175,"mergedPRs":7446,"closedPRs":2591,"openPRs":248,"openIssues":6007,"timestamp":1631261013},{"stars":121169,"closedPRs":2591,"openPRs":249,"timestamp":1631257375,"mergedPRs":7445,"openIssues":5998,"closedIssues":113602},{"openPRs":249,"closedIssues":113597,"openIssues":6002,"mergedPRs":7445,"timestamp":1631253784,"closedPRs":2591,"stars":121165},{"closedIssues":113597,"openIssues":6001,"openPRs":248,"mergedPRs":7445,"closedPRs":2591,"stars":121164,"timestamp":1631250175},{"closedPRs":2591,"openIssues":6000,"mergedPRs":7445,"timestamp":1631246592,"openPRs":248,"closedIssues":113596,"stars":121164},{"openIssues":5997,"stars":121165,"closedPRs":2591,"timestamp":1631242984,"openPRs":248,"mergedPRs":7445,"closedIssues":113593},{"timestamp":1631240025,"closedIssues":113591,"mergedPRs":7445,"closedPRs":2591,"openIssues":5997,"openPRs":248,"stars":121165},{"timestamp":1631237092,"openIssues":5998,"closedIssues":113588,"stars":121165,"openPRs":247,"closedPRs":2591,"mergedPRs":7445},{"mergedPRs":7445,"timestamp":1631232316,"stars":121162,"openIssues":5997,"openPRs":247,"closedPRs":2591,"closedIssues":113584},{"openPRs":246,"openIssues":6001,"stars":121162,"timestamp":1631228587,"closedIssues":113579,"mergedPRs":7445,"closedPRs":2591},{"closedPRs":2591,"closedIssues":113576,"openPRs":246,"stars":121161,"openIssues":6002,"timestamp":1631224993,"mergedPRs":7443},{"closedIssues":113572,"closedPRs":2591,"mergedPRs":7441,"openPRs":248,"stars":121159,"openIssues":6001,"timestamp":1631221392},{"openIssues":6003,"stars":121157,"closedIssues":113564,"closedPRs":2591,"timestamp":1631217791,"mergedPRs":7440,"openPRs":248},{"mergedPRs":7439,"stars":121156,"openIssues":6014,"closedPRs":2590,"timestamp":1631214178,"openPRs":248,"closedIssues":113553},{"timestamp":1631210589,"mergedPRs":7439,"stars":121154,"openPRs":247,"closedIssues":113552,"openIssues":6005,"closedPRs":2590},{"closedIssues":113549,"openPRs":247,"closedPRs":2590,"timestamp":1631207232,"stars":121153,"mergedPRs":7439,"openIssues":6005},{"mergedPRs":7438,"openPRs":248,"stars":121153,"closedIssues":113547,"openIssues":6001,"timestamp":1631203388,"closedPRs":2590},{"closedIssues":113547,"openPRs":247,"closedPRs":2590,"openIssues":5996,"mergedPRs":7438,"timestamp":1631199804,"stars":121150},{"stars":121147,"closedPRs":2589,"closedIssues":113541,"timestamp":1631196200,"openPRs":248,"mergedPRs":7438,"openIssues":5999},{"closedPRs":2589,"stars":121144,"timestamp":1631192856,"openPRs":248,"mergedPRs":7438,"closedIssues":113539,"openIssues":5995},{"closedIssues":113537,"closedPRs":2589,"stars":121144,"timestamp":1631189208,"openIssues":5993,"openPRs":247,"mergedPRs":7438},{"stars":121142,"closedIssues":113532,"closedPRs":2589,"mergedPRs":7438,"openPRs":247,"openIssues":5994,"timestamp":1631185393},{"closedIssues":113531,"mergedPRs":7438,"timestamp":1631181786,"openPRs":248,"openIssues":5991,"stars":121138,"closedPRs":2588},{"stars":121134,"closedIssues":113529,"openPRs":248,"closedPRs":2588,"mergedPRs":7438,"timestamp":1631178186,"openIssues":5992},{"openIssues":5991,"openPRs":248,"closedPRs":2588,"stars":121132,"mergedPRs":7438,"closedIssues":113526,"timestamp":1631174625},{"closedIssues":113519,"timestamp":1631171287,"openIssues":5990,"openPRs":250,"mergedPRs":7437,"closedPRs":2587,"stars":121126},{"closedIssues":113518,"openIssues":5985,"timestamp":1631167387,"openPRs":253,"closedPRs":2587,"stars":121123,"mergedPRs":7434},{"closedPRs":2587,"mergedPRs":7434,"timestamp":1631163781,"openIssues":5984,"openPRs":253,"closedIssues":113517,"stars":121121},{"closedPRs":2587,"timestamp":1631160194,"stars":121119,"mergedPRs":7434,"openPRs":253,"openIssues":5981,"closedIssues":113517},{"openPRs":253,"timestamp":1631156572,"closedPRs":2587,"closedIssues":113517,"mergedPRs":7434,"stars":121117,"openIssues":5979},{"closedPRs":2587,"closedIssues":113515,"openPRs":253,"stars":121114,"timestamp":1631153613,"openIssues":5976,"mergedPRs":7434},{"stars":121114,"timestamp":1631150697,"closedPRs":2587,"openIssues":5974,"mergedPRs":7434,"closedIssues":113514,"openPRs":253},{"closedIssues":113513,"openPRs":253,"stars":121114,"closedPRs":2587,"openIssues":5974,"timestamp":1631145920,"mergedPRs":7434},{"closedIssues":113513,"openIssues":5971,"stars":121113,"timestamp":1631142184,"openPRs":253,"mergedPRs":7434,"closedPRs":2587},{"stars":121112,"timestamp":1631138584,"mergedPRs":7434,"openIssues":5967,"closedPRs":2587,"closedIssues":113510,"openPRs":253},{"timestamp":1631134980,"closedIssues":113509,"closedPRs":2587,"mergedPRs":7434,"openPRs":252,"stars":121113,"openIssues":5967},{"stars":121109,"timestamp":1631131376,"openPRs":252,"closedIssues":113506,"openIssues":5966,"mergedPRs":7434,"closedPRs":2587},{"openIssues":5964,"closedPRs":2587,"closedIssues":113504,"timestamp":1631127780,"openPRs":252,"mergedPRs":7434,"stars":121109},{"closedIssues":113500,"closedPRs":2586,"mergedPRs":7434,"stars":121105,"openIssues":5967,"openPRs":252,"timestamp":1631124259},{"mergedPRs":7434,"closedPRs":2586,"openIssues":5965,"openPRs":252,"timestamp":1631120832,"stars":121105,"closedIssues":113499},{"openPRs":252,"timestamp":1631117008,"closedIssues":113491,"stars":121102,"mergedPRs":7433,"closedPRs":2586,"openIssues":5963},{"openIssues":5960,"mergedPRs":7433,"stars":121101,"closedIssues":113487,"openPRs":252,"closedPRs":2585,"timestamp":1631113371},{"stars":121095,"closedIssues":113485,"mergedPRs":7433,"openPRs":252,"closedPRs":2585,"timestamp":1631109783,"openIssues":5957},{"openIssues":5954,"closedIssues":113482,"timestamp":1631106452,"closedPRs":2584,"mergedPRs":7433,"openPRs":253,"stars":121095},{"closedPRs":2583,"mergedPRs":7433,"closedIssues":113478,"openPRs":254,"stars":121094,"timestamp":1631102611,"openIssues":5957},{"stars":121089,"closedPRs":2583,"openPRs":255,"timestamp":1631098973,"mergedPRs":7432,"openIssues":5995,"closedIssues":113437},{"openPRs":255,"mergedPRs":7432,"closedPRs":2583,"closedIssues":113437,"openIssues":5993,"stars":121087,"timestamp":1631095419},{"timestamp":1631091788,"openIssues":5989,"stars":121088,"closedIssues":113434,"openPRs":254,"mergedPRs":7432,"closedPRs":2583},{"closedPRs":2583,"openPRs":253,"openIssues":5994,"timestamp":1631088206,"stars":121083,"closedIssues":113428,"mergedPRs":7431},{"closedIssues":113426,"timestamp":1631084597,"openIssues":5990,"openPRs":252,"mergedPRs":7431,"stars":121078,"closedPRs":2583},{"openPRs":252,"openIssues":5992,"closedIssues":113420,"stars":121076,"mergedPRs":7431,"timestamp":1631080996,"closedPRs":2583},{"timestamp":1631077367,"openPRs":252,"stars":121073,"closedIssues":113420,"closedPRs":2583,"mergedPRs":7431,"openIssues":5990},{"timestamp":1631073798,"mergedPRs":7431,"openPRs":252,"closedPRs":2583,"stars":121073,"closedIssues":113420,"openIssues":5986},{"openPRs":252,"closedIssues":113419,"mergedPRs":7431,"openIssues":5985,"stars":121074,"closedPRs":2583,"timestamp":1631070195},{"stars":121072,"mergedPRs":7431,"closedPRs":2583,"closedIssues":113402,"timestamp":1631067092,"openIssues":5997,"openPRs":252},{"stars":121069,"mergedPRs":7431,"closedPRs":2583,"timestamp":1631064193,"openPRs":252,"closedIssues":113400,"openIssues":5995},{"timestamp":1631059460,"openIssues":5995,"stars":121066,"closedPRs":2583,"openPRs":252,"closedIssues":113399,"mergedPRs":7431},{"stars":121066,"closedPRs":2583,"closedIssues":113393,"mergedPRs":7431,"openIssues":6000,"openPRs":252,"timestamp":1631055789},{"closedPRs":2582,"stars":121066,"closedIssues":113389,"openIssues":6002,"openPRs":252,"timestamp":1631052193,"mergedPRs":7431},{"openPRs":252,"closedIssues":113379,"timestamp":1631048583,"closedPRs":2580,"mergedPRs":7430,"stars":121066,"openIssues":6009},{"mergedPRs":7428,"openPRs":254,"closedPRs":2579,"stars":121062,"closedIssues":113371,"timestamp":1631044992,"openIssues":6015},{"closedIssues":113366,"closedPRs":2579,"openIssues":6017,"mergedPRs":7428,"timestamp":1631041369,"openPRs":253,"stars":121063},{"closedPRs":2579,"timestamp":1631037788,"openIssues":6016,"openPRs":254,"closedIssues":113365,"mergedPRs":7427,"stars":121060},{"openIssues":6015,"openPRs":253,"timestamp":1631034442,"closedIssues":113360,"closedPRs":2579,"mergedPRs":7427,"stars":121058},{"timestamp":1631030598,"closedPRs":2579,"stars":121056,"openIssues":6016,"openPRs":253,"mergedPRs":7427,"closedIssues":113355},{"stars":121054,"timestamp":1631026988,"closedIssues":113342,"openIssues":6027,"mergedPRs":7426,"closedPRs":2579,"openPRs":254},{"closedIssues":113329,"openIssues":6032,"timestamp":1631023386,"closedPRs":2579,"mergedPRs":7426,"openPRs":254,"stars":121053},{"closedPRs":2579,"mergedPRs":7426,"timestamp":1631020337,"openPRs":254,"closedIssues":113326,"stars":121053,"openIssues":6032},{"openPRs":255,"closedPRs":2579,"stars":121052,"closedIssues":113319,"timestamp":1631016197,"mergedPRs":7425,"openIssues":6033},{"openIssues":6031,"closedPRs":2579,"timestamp":1631012889,"openPRs":254,"stars":121052,"closedIssues":113318,"mergedPRs":7425},{"closedIssues":113315,"openPRs":254,"mergedPRs":7425,"timestamp":1631009281,"openIssues":6029,"stars":121050,"closedPRs":2578},{"openIssues":6030,"closedIssues":113312,"openPRs":253,"mergedPRs":7425,"stars":121048,"timestamp":1631005675,"closedPRs":2578},{"mergedPRs":7425,"stars":121040,"openIssues":6028,"openPRs":251,"timestamp":1631002093,"closedPRs":2578,"closedIssues":113309},{"openIssues":6026,"closedIssues":113307,"openPRs":251,"timestamp":1630998175,"mergedPRs":7425,"stars":121034,"closedPRs":2577},{"closedPRs":2577,"closedIssues":113295,"openIssues":6037,"openPRs":249,"mergedPRs":7425,"timestamp":1630994592,"stars":121032},{"mergedPRs":7425,"closedIssues":113293,"stars":121031,"openIssues":6038,"closedPRs":2577,"timestamp":1630990972,"openPRs":249},{"closedIssues":113292,"openIssues":6037,"openPRs":249,"mergedPRs":7425,"closedPRs":2577,"timestamp":1630987385,"stars":121030},{"stars":121024,"closedIssues":113291,"closedPRs":2577,"mergedPRs":7425,"openIssues":6037,"timestamp":1630983781,"openPRs":248},{"closedPRs":2577,"openPRs":247,"openIssues":6035,"timestamp":1630980673,"mergedPRs":7425,"closedIssues":113290,"stars":121023},{"openPRs":247,"closedIssues":113284,"openIssues":6040,"closedPRs":2577,"timestamp":1630977756,"stars":121019,"mergedPRs":7424},{"timestamp":1630973090,"closedPRs":2577,"openIssues":6038,"openPRs":247,"stars":121016,"closedIssues":113284,"mergedPRs":7424},{"openIssues":6037,"closedPRs":2577,"openPRs":246,"mergedPRs":7424,"timestamp":1630969378,"stars":121016,"closedIssues":113284},{"closedIssues":113283,"mergedPRs":7424,"openIssues":6036,"timestamp":1630965790,"closedPRs":2577,"stars":121015,"openPRs":246},{"timestamp":1630962176,"closedIssues":113283,"stars":121013,"openIssues":6036,"openPRs":246,"closedPRs":2577,"mergedPRs":7424},{"closedPRs":2577,"timestamp":1630958596,"stars":121009,"openIssues":6035,"openPRs":245,"mergedPRs":7424,"closedIssues":113283},{"timestamp":1630954990,"stars":121008,"openPRs":245,"closedIssues":113281,"openIssues":6034,"mergedPRs":7424,"closedPRs":2577},{"openPRs":245,"closedIssues":113280,"mergedPRs":7424,"timestamp":1630951371,"stars":121006,"closedPRs":2577,"openIssues":6033},{"mergedPRs":7424,"closedPRs":2577,"openPRs":245,"stars":121004,"timestamp":1630948046,"closedIssues":113279,"openIssues":6034},{"timestamp":1630944179,"openIssues":6038,"closedPRs":2577,"openPRs":245,"closedIssues":113271,"mergedPRs":7424,"stars":121001},{"openPRs":244,"mergedPRs":7424,"timestamp":1630940593,"closedIssues":113271,"stars":121000,"closedPRs":2577,"openIssues":6034},{"mergedPRs":7424,"timestamp":1630936986,"stars":120997,"openIssues":6033,"closedIssues":113265,"openPRs":243,"closedPRs":2577},{"openPRs":242,"stars":120995,"mergedPRs":7424,"timestamp":1630933930,"closedPRs":2577,"closedIssues":113261,"openIssues":6031},{"closedPRs":2576,"openIssues":6042,"openPRs":244,"stars":120993,"timestamp":1630930079,"closedIssues":113240,"mergedPRs":7423},{"timestamp":1630926476,"mergedPRs":7423,"stars":120992,"closedIssues":113238,"closedPRs":2576,"openPRs":244,"openIssues":6040},{"timestamp":1630922875,"mergedPRs":7423,"closedPRs":2576,"openIssues":6040,"openPRs":244,"stars":120994,"closedIssues":113231},{"stars":120993,"closedIssues":113227,"timestamp":1630919291,"openPRs":244,"openIssues":6039,"mergedPRs":7423,"closedPRs":2576},{"timestamp":1630915702,"openIssues":6035,"closedIssues":113226,"stars":120990,"mergedPRs":7423,"openPRs":244,"closedPRs":2576},{"timestamp":1630911769,"stars":120985,"closedPRs":2576,"closedIssues":113224,"mergedPRs":7422,"openPRs":244,"openIssues":6033},{"closedIssues":113220,"openIssues":6032,"closedPRs":2576,"timestamp":1630908187,"mergedPRs":7421,"stars":120981,"openPRs":245},{"mergedPRs":7421,"timestamp":1630904586,"closedIssues":113220,"openIssues":6029,"openPRs":245,"closedPRs":2576,"stars":120983},{"mergedPRs":7421,"stars":120983,"timestamp":1630900998,"openPRs":245,"openIssues":6028,"closedPRs":2576,"closedIssues":113220},{"closedPRs":2576,"openPRs":245,"closedIssues":113220,"mergedPRs":7421,"openIssues":6026,"timestamp":1630897387,"stars":120979},{"closedIssues":113220,"stars":120976,"timestamp":1630894469,"mergedPRs":7421,"openPRs":245,"closedPRs":2576,"openIssues":6025},{"closedIssues":113220,"mergedPRs":7421,"stars":120976,"openIssues":6024,"timestamp":1630891516,"openPRs":245,"closedPRs":2576},{"timestamp":1630886692,"closedPRs":2576,"openIssues":6023,"closedIssues":113219,"mergedPRs":7421,"openPRs":245,"stars":120974},{"stars":120974,"openIssues":6022,"timestamp":1630882979,"closedIssues":113219,"openPRs":245,"closedPRs":2576,"mergedPRs":7421},{"stars":120973,"closedPRs":2576,"openPRs":245,"mergedPRs":7421,"openIssues":6020,"timestamp":1630879395,"closedIssues":113219},{"closedPRs":2576,"closedIssues":113219,"openIssues":6018,"timestamp":1630875782,"stars":120973,"openPRs":245,"mergedPRs":7421},{"openIssues":6021,"closedPRs":2576,"mergedPRs":7421,"stars":120971,"timestamp":1630872195,"openPRs":245,"closedIssues":113215},{"closedPRs":2576,"openIssues":6019,"mergedPRs":7421,"openPRs":245,"stars":120971,"timestamp":1630868574,"closedIssues":113213},{"openPRs":244,"stars":120970,"timestamp":1630864971,"closedPRs":2576,"mergedPRs":7421,"closedIssues":113211,"openIssues":6020},{"openIssues":6018,"stars":120969,"openPRs":244,"closedPRs":2576,"timestamp":1630861594,"closedIssues":113210,"mergedPRs":7421},{"closedIssues":113209,"openPRs":244,"mergedPRs":7421,"stars":120968,"openIssues":6018,"timestamp":1630857790,"closedPRs":2576},{"closedIssues":113209,"mergedPRs":7421,"timestamp":1630854191,"openPRs":244,"closedPRs":2576,"stars":120967,"openIssues":6015},{"closedPRs":2576,"timestamp":1630850572,"mergedPRs":7421,"stars":120963,"openIssues":6013,"closedIssues":113208,"openPRs":244},{"openIssues":6015,"openPRs":244,"stars":120962,"closedIssues":113206,"mergedPRs":7421,"closedPRs":2576,"timestamp":1630847202},{"openPRs":244,"closedPRs":2576,"openIssues":6013,"stars":120963,"closedIssues":113206,"mergedPRs":7421,"timestamp":1630843386},{"timestamp":1630839775,"closedIssues":113205,"closedPRs":2576,"openIssues":6009,"openPRs":244,"mergedPRs":7421,"stars":120960},{"closedIssues":113204,"openPRs":244,"closedPRs":2576,"timestamp":1630836190,"mergedPRs":7421,"openIssues":6008,"stars":120957},{"stars":120956,"openPRs":244,"openIssues":6005,"closedPRs":2576,"timestamp":1630832586,"closedIssues":113204,"mergedPRs":7421},{"openPRs":244,"mergedPRs":7421,"closedIssues":113204,"openIssues":6001,"stars":120956,"timestamp":1630828983,"closedPRs":2576},{"closedIssues":113203,"closedPRs":2576,"stars":120954,"openIssues":6001,"mergedPRs":7421,"openPRs":244,"timestamp":1630825360},{"openIssues":5999,"mergedPRs":7421,"stars":120953,"openPRs":244,"closedPRs":2576,"timestamp":1630821777,"closedIssues":113203},{"openPRs":244,"closedIssues":113203,"stars":120951,"timestamp":1630818167,"closedPRs":2576,"mergedPRs":7421,"openIssues":5999},{"openPRs":244,"mergedPRs":7421,"stars":120947,"closedIssues":113202,"openIssues":5999,"timestamp":1630814599,"closedPRs":2576},{"timestamp":1630810980,"openPRs":244,"stars":120944,"closedPRs":2576,"mergedPRs":7421,"closedIssues":113193,"openIssues":6006},{"mergedPRs":7421,"closedIssues":113192,"timestamp":1630807972,"stars":120944,"openIssues":6006,"closedPRs":2576,"openPRs":244},{"closedPRs":2576,"mergedPRs":7421,"timestamp":1630805078,"openPRs":244,"closedIssues":113192,"openIssues":6003,"stars":120941},{"stars":120940,"openPRs":244,"mergedPRs":7421,"timestamp":1630800319,"openIssues":6003,"closedIssues":113191,"closedPRs":2576},{"openPRs":244,"timestamp":1630796581,"mergedPRs":7421,"stars":120937,"closedPRs":2576,"openIssues":6002,"closedIssues":113191},{"stars":120936,"openIssues":6002,"closedIssues":113190,"mergedPRs":7421,"openPRs":244,"closedPRs":2576,"timestamp":1630792988},{"timestamp":1630789386,"mergedPRs":7421,"openIssues":5999,"openPRs":244,"closedPRs":2576,"stars":120935,"closedIssues":113190},{"openIssues":5996,"openPRs":244,"mergedPRs":7421,"closedPRs":2576,"closedIssues":113190,"stars":120932,"timestamp":1630785777},{"timestamp":1630782165,"openPRs":244,"stars":120928,"closedPRs":2576,"mergedPRs":7421,"closedIssues":113190,"openIssues":5994},{"timestamp":1630778575,"stars":120923,"mergedPRs":7421,"openIssues":5998,"openPRs":244,"closedPRs":2576,"closedIssues":113185},{"stars":120920,"closedPRs":2576,"closedIssues":113184,"openIssues":5997,"timestamp":1630775184,"openPRs":244,"mergedPRs":7421},{"mergedPRs":7421,"openPRs":244,"timestamp":1630771399,"stars":120918,"closedPRs":2576,"closedIssues":113184,"openIssues":5995},{"stars":120917,"openPRs":244,"timestamp":1630767797,"closedPRs":2576,"mergedPRs":7421,"closedIssues":113182,"openIssues":5994},{"closedIssues":113182,"timestamp":1630764172,"mergedPRs":7421,"openPRs":244,"closedPRs":2576,"openIssues":5992,"stars":120914},{"closedIssues":113182,"mergedPRs":7421,"stars":120912,"closedPRs":2576,"openIssues":5987,"openPRs":244,"timestamp":1630760784},{"closedIssues":113180,"openIssues":5988,"timestamp":1630757002,"stars":120912,"mergedPRs":7421,"closedPRs":2576,"openPRs":244},{"closedPRs":2576,"mergedPRs":7421,"stars":120910,"openIssues":5989,"timestamp":1630753373,"openPRs":244,"closedIssues":113179},{"closedIssues":113179,"openIssues":5987,"mergedPRs":7421,"openPRs":244,"closedPRs":2576,"stars":120907,"timestamp":1630749775},{"stars":120905,"mergedPRs":7421,"timestamp":1630746204,"openPRs":244,"closedPRs":2576,"closedIssues":113178,"openIssues":5986},{"timestamp":1630742583,"stars":120903,"mergedPRs":7421,"closedPRs":2576,"openIssues":5986,"openPRs":244,"closedIssues":113175},{"openPRs":243,"closedIssues":113172,"timestamp":1630738986,"stars":120903,"openIssues":5986,"mergedPRs":7421,"closedPRs":2576},{"openPRs":243,"closedIssues":113172,"closedPRs":2576,"mergedPRs":7421,"stars":120904,"timestamp":1630735375,"openIssues":5985},{"closedPRs":2576,"openPRs":243,"mergedPRs":7421,"stars":120904,"openIssues":5983,"timestamp":1630731771,"closedIssues":113172},{"openIssues":5982,"timestamp":1630728189,"stars":120904,"mergedPRs":7421,"openPRs":243,"closedPRs":2576,"closedIssues":113172},{"mergedPRs":7421,"timestamp":1630724574,"openPRs":243,"closedIssues":113171,"openIssues":5983,"stars":120903,"closedPRs":2576},{"closedIssues":113170,"mergedPRs":7421,"timestamp":1630721648,"stars":120903,"closedPRs":2576,"openIssues":5982,"openPRs":243},{"stars":120904,"closedPRs":2576,"openIssues":5982,"closedIssues":113168,"mergedPRs":7421,"timestamp":1630718624,"openPRs":242},{"openPRs":242,"closedIssues":113166,"mergedPRs":7421,"closedPRs":2576,"stars":120904,"openIssues":5980,"timestamp":1630713880},{"openIssues":5980,"timestamp":1630710175,"mergedPRs":7421,"closedIssues":113162,"closedPRs":2576,"stars":120902,"openPRs":242},{"mergedPRs":7421,"openPRs":242,"openIssues":5983,"closedPRs":2576,"timestamp":1630706583,"stars":120901,"closedIssues":113156},{"closedPRs":2576,"closedIssues":113155,"mergedPRs":7421,"stars":120898,"openIssues":5983,"timestamp":1630702963,"openPRs":242},{"stars":120895,"openIssues":5981,"closedIssues":113154,"openPRs":242,"timestamp":1630699377,"closedPRs":2576,"mergedPRs":7420},{"closedIssues":113152,"mergedPRs":7418,"stars":120894,"timestamp":1630695770,"openPRs":247,"closedPRs":2573,"openIssues":5982},{"closedIssues":113150,"mergedPRs":7418,"timestamp":1630692195,"openPRs":246,"stars":120891,"closedPRs":2573,"openIssues":5975},{"closedIssues":113149,"mergedPRs":7418,"openPRs":246,"timestamp":1630688836,"closedPRs":2573,"openIssues":5973,"stars":120890},{"openPRs":246,"openIssues":5973,"timestamp":1630685276,"mergedPRs":7418,"closedPRs":2573,"closedIssues":113146,"stars":120891},{"stars":120891,"closedPRs":2573,"mergedPRs":7418,"openIssues":5967,"timestamp":1630681681,"closedIssues":113144,"openPRs":246},{"openPRs":245,"closedIssues":113143,"stars":120888,"openIssues":5959,"closedPRs":2573,"timestamp":1630678077,"mergedPRs":7418},{"closedIssues":113140,"mergedPRs":7418,"closedPRs":2573,"openIssues":5956,"openPRs":245,"timestamp":1630674730,"stars":120883},{"closedIssues":113139,"openPRs":245,"stars":120880,"openIssues":5955,"closedPRs":2573,"timestamp":1630670646,"mergedPRs":7418},{"openIssues":5956,"closedIssues":113132,"stars":120877,"timestamp":1630667059,"openPRs":245,"mergedPRs":7418,"closedPRs":2573},{"mergedPRs":7418,"timestamp":1630663674,"openIssues":5956,"openPRs":242,"stars":120876,"closedIssues":113129,"closedPRs":2573},{"openPRs":242,"openIssues":5944,"timestamp":1630660078,"stars":120873,"closedPRs":2573,"mergedPRs":7418,"closedIssues":113128},{"openPRs":242,"mergedPRs":7418,"stars":120868,"timestamp":1630656470,"closedPRs":2573,"closedIssues":113123,"openIssues":5942},{"mergedPRs":7418,"openIssues":5936,"closedIssues":113123,"stars":120862,"openPRs":242,"closedPRs":2573,"timestamp":1630652563}]
