[{"closedIssues":119242,"openPRs":244,"timestamp":1638604998,"mergedPRs":7819,"openIssues":5117,"closedPRs":2743,"stars":124865},{"mergedPRs":7819,"openPRs":244,"stars":124860,"closedPRs":2743,"closedIssues":119242,"timestamp":1638601394,"openIssues":5116},{"openPRs":244,"closedIssues":119241,"mergedPRs":7819,"timestamp":1638598025,"stars":124859,"openIssues":5116,"closedPRs":2743},{"openPRs":244,"openIssues":5116,"closedIssues":119241,"mergedPRs":7819,"stars":124858,"timestamp":1638594198,"closedPRs":2743},{"closedIssues":119241,"closedPRs":2743,"mergedPRs":7819,"openPRs":244,"stars":124860,"timestamp":1638590590,"openIssues":5114},{"openPRs":244,"stars":124858,"mergedPRs":7819,"openIssues":5112,"timestamp":1638587000,"closedPRs":2743,"closedIssues":119240},{"openPRs":243,"mergedPRs":7819,"closedIssues":119234,"timestamp":1638584100,"openIssues":5118,"stars":124858,"closedPRs":2743},{"closedIssues":119234,"openIssues":5118,"mergedPRs":7819,"stars":124856,"timestamp":1638581061,"closedPRs":2743,"openPRs":243},{"openPRs":243,"timestamp":1638576351,"closedPRs":2743,"stars":124856,"closedIssues":119234,"mergedPRs":7819,"openIssues":5117},{"openPRs":243,"timestamp":1638572597,"mergedPRs":7819,"openIssues":5117,"closedPRs":2743,"stars":124856,"closedIssues":119234},{"openPRs":242,"mergedPRs":7819,"stars":124856,"openIssues":5117,"closedPRs":2743,"timestamp":1638569006,"closedIssues":119234},{"stars":124856,"openPRs":242,"closedIssues":119230,"timestamp":1638565417,"openIssues":5120,"mergedPRs":7819,"closedPRs":2743},{"openIssues":5123,"closedPRs":2742,"stars":124856,"timestamp":1638561791,"openPRs":243,"closedIssues":119227,"mergedPRs":7819},{"openIssues":5122,"mergedPRs":7819,"closedIssues":119225,"stars":124854,"openPRs":243,"closedPRs":2742,"timestamp":1638558204},{"openIssues":5124,"timestamp":1638554593,"closedPRs":2742,"stars":124851,"openPRs":242,"closedIssues":119220,"mergedPRs":7819},{"openIssues":5123,"timestamp":1638551269,"openPRs":239,"closedPRs":2742,"mergedPRs":7819,"stars":124850,"closedIssues":119219},{"openIssues":5128,"mergedPRs":7819,"stars":124847,"closedPRs":2742,"closedIssues":119213,"openPRs":239,"timestamp":1638547419},{"stars":124846,"mergedPRs":7819,"openPRs":239,"closedIssues":119212,"closedPRs":2742,"openIssues":5124,"timestamp":1638543830},{"timestamp":1638540212,"mergedPRs":7819,"openPRs":239,"closedPRs":2742,"stars":124841,"openIssues":5123,"closedIssues":119210},{"stars":124839,"timestamp":1638536855,"openPRs":239,"openIssues":5122,"mergedPRs":7819,"closedPRs":2742,"closedIssues":119208},{"timestamp":1638533166,"openPRs":239,"stars":124835,"closedPRs":2742,"closedIssues":119207,"openIssues":5122,"mergedPRs":7819},{"timestamp":1638529398,"stars":124832,"openPRs":239,"mergedPRs":7819,"closedIssues":119200,"closedPRs":2742,"openIssues":5127},{"mergedPRs":7819,"timestamp":1638525803,"openIssues":5128,"closedIssues":119197,"openPRs":239,"closedPRs":2742,"stars":124832},{"openIssues":5125,"stars":124830,"timestamp":1638522198,"closedPRs":2742,"openPRs":238,"closedIssues":119197,"mergedPRs":7819},{"closedIssues":119194,"timestamp":1638518638,"mergedPRs":7818,"openIssues":5129,"openPRs":239,"closedPRs":2742,"stars":124827},{"openIssues":5127,"openPRs":239,"closedIssues":119194,"closedPRs":2742,"stars":124827,"timestamp":1638514990,"mergedPRs":7818},{"closedIssues":119194,"timestamp":1638511417,"openPRs":239,"stars":124817,"openIssues":5125,"closedPRs":2742,"mergedPRs":7818},{"openPRs":239,"mergedPRs":7818,"closedPRs":2742,"stars":124814,"openIssues":5125,"closedIssues":119194,"timestamp":1638507804},{"stars":124812,"closedIssues":119194,"openPRs":239,"timestamp":1638504204,"mergedPRs":7818,"closedPRs":2742,"openIssues":5122},{"timestamp":1638500592,"openPRs":239,"mergedPRs":7818,"closedIssues":119193,"stars":124813,"closedPRs":2742,"openIssues":5119},{"closedIssues":119193,"closedPRs":2742,"mergedPRs":7818,"openIssues":5117,"stars":124812,"timestamp":1638497668,"openPRs":239},{"closedIssues":119193,"stars":124811,"openIssues":5117,"timestamp":1638494669,"openPRs":239,"mergedPRs":7818,"closedPRs":2742},{"closedIssues":119193,"mergedPRs":7818,"timestamp":1638489965,"closedPRs":2742,"stars":124808,"openPRs":239,"openIssues":5116},{"openPRs":239,"closedIssues":119191,"openIssues":5117,"closedPRs":2742,"mergedPRs":7818,"stars":124807,"timestamp":1638486229},{"stars":124804,"openIssues":5117,"timestamp":1638482622,"closedPRs":2741,"mergedPRs":7818,"closedIssues":119187,"openPRs":240},{"mergedPRs":7818,"stars":124804,"closedIssues":119187,"timestamp":1638479013,"openPRs":240,"openIssues":5114,"closedPRs":2741},{"timestamp":1638475397,"openPRs":240,"stars":124802,"mergedPRs":7818,"openIssues":5110,"closedPRs":2741,"closedIssues":119184},{"stars":124802,"closedIssues":119182,"timestamp":1638471785,"openPRs":240,"openIssues":5108,"closedPRs":2741,"mergedPRs":7818},{"closedPRs":2741,"timestamp":1638468200,"stars":124798,"openIssues":5108,"mergedPRs":7818,"closedIssues":119179,"openPRs":240},{"stars":124797,"closedPRs":2741,"timestamp":1638465124,"mergedPRs":7818,"closedIssues":119177,"openPRs":240,"openIssues":5111},{"openPRs":239,"openIssues":5107,"closedPRs":2741,"timestamp":1638461007,"closedIssues":119175,"mergedPRs":7817,"stars":124796},{"timestamp":1638457481,"openPRs":239,"closedIssues":119174,"closedPRs":2741,"mergedPRs":7817,"stars":124794,"openIssues":5106},{"openPRs":240,"mergedPRs":7816,"timestamp":1638453831,"openIssues":5103,"stars":124790,"closedPRs":2741,"closedIssues":119173},{"closedPRs":2741,"timestamp":1638450446,"stars":124787,"mergedPRs":7816,"closedIssues":119173,"openIssues":5102,"openPRs":240},{"timestamp":1638446616,"closedIssues":119171,"openIssues":5103,"openPRs":240,"mergedPRs":7816,"closedPRs":2741,"stars":124783},{"closedIssues":119164,"stars":124781,"openIssues":5106,"openPRs":240,"timestamp":1638443042,"closedPRs":2741,"mergedPRs":7816},{"mergedPRs":7815,"openPRs":240,"timestamp":1638439426,"closedIssues":119159,"closedPRs":2741,"stars":124779,"openIssues":5108},{"closedIssues":119158,"stars":124776,"closedPRs":2741,"openPRs":240,"openIssues":5104,"timestamp":1638435801,"mergedPRs":7815},{"closedPRs":2740,"timestamp":1638432223,"openPRs":242,"closedIssues":119155,"openIssues":5104,"mergedPRs":7814,"stars":124776},{"openPRs":242,"timestamp":1638428621,"closedPRs":2740,"mergedPRs":7814,"closedIssues":119154,"openIssues":5101,"stars":124776},{"closedPRs":2740,"openPRs":242,"closedIssues":119153,"mergedPRs":7814,"stars":124775,"timestamp":1638425009,"openIssues":5099},{"openPRs":242,"mergedPRs":7814,"stars":124774,"closedIssues":119152,"closedPRs":2740,"openIssues":5098,"timestamp":1638421400},{"mergedPRs":7814,"openIssues":5097,"closedIssues":119151,"closedPRs":2740,"stars":124772,"timestamp":1638417801,"openPRs":242},{"stars":124771,"timestamp":1638414195,"openPRs":242,"closedIssues":119151,"mergedPRs":7814,"openIssues":5094,"closedPRs":2740},{"closedIssues":119150,"openPRs":242,"closedPRs":2740,"mergedPRs":7814,"openIssues":5095,"stars":124768,"timestamp":1638411277},{"closedPRs":2740,"mergedPRs":7814,"openIssues":5095,"stars":124766,"openPRs":242,"timestamp":1638408285,"closedIssues":119149},{"mergedPRs":7813,"closedIssues":119145,"openIssues":5097,"stars":124765,"openPRs":243,"closedPRs":2740,"timestamp":1638403593},{"stars":124763,"closedPRs":2740,"openIssues":5100,"openPRs":241,"mergedPRs":7813,"closedIssues":119140,"timestamp":1638399817},{"openPRs":242,"mergedPRs":7812,"stars":124762,"timestamp":1638396204,"closedPRs":2740,"closedIssues":119135,"openIssues":5102},{"openIssues":5109,"timestamp":1638392592,"stars":124761,"closedPRs":2740,"openPRs":244,"mergedPRs":7810,"closedIssues":119127},{"closedIssues":119127,"timestamp":1638389016,"stars":124758,"closedPRs":2740,"mergedPRs":7810,"openPRs":244,"openIssues":5108},{"timestamp":1638385694,"closedIssues":119124,"openPRs":244,"openIssues":5107,"mergedPRs":7810,"closedPRs":2739,"stars":124752},{"openPRs":243,"closedIssues":119120,"stars":124750,"timestamp":1638382093,"mergedPRs":7810,"closedPRs":2739,"openIssues":5111},{"openIssues":5113,"openPRs":242,"mergedPRs":7810,"timestamp":1638378794,"stars":124750,"closedPRs":2739,"closedIssues":119116},{"openPRs":238,"mergedPRs":7810,"openIssues":5119,"timestamp":1638374907,"stars":124751,"closedPRs":2739,"closedIssues":119107},{"closedPRs":2739,"stars":124748,"openPRs":238,"timestamp":1638371298,"closedIssues":119104,"openIssues":5113,"mergedPRs":7810},{"timestamp":1638367401,"openIssues":5112,"closedIssues":119098,"stars":124745,"closedPRs":2739,"mergedPRs":7810,"openPRs":238},{"openPRs":238,"closedIssues":119095,"timestamp":1638364091,"mergedPRs":7810,"stars":124743,"openIssues":5115,"closedPRs":2739},{"openPRs":236,"closedPRs":2739,"openIssues":5115,"stars":124741,"timestamp":1638360230,"closedIssues":119093,"mergedPRs":7810},{"closedIssues":119085,"openIssues":5121,"timestamp":1638356892,"mergedPRs":7810,"openPRs":236,"stars":124738,"closedPRs":2739},{"openIssues":5118,"closedPRs":2739,"stars":124738,"mergedPRs":7810,"closedIssues":119083,"timestamp":1638353307,"openPRs":236},{"closedPRs":2739,"openIssues":5119,"timestamp":1638349707,"closedIssues":119078,"stars":124734,"mergedPRs":7810,"openPRs":236},{"mergedPRs":7810,"stars":124733,"openIssues":5119,"closedIssues":119076,"openPRs":236,"timestamp":1638345819,"closedPRs":2739},{"openPRs":236,"closedPRs":2739,"closedIssues":119075,"mergedPRs":7810,"stars":124732,"openIssues":5120,"timestamp":1638342196},{"mergedPRs":7810,"stars":124732,"closedPRs":2739,"closedIssues":119073,"openPRs":236,"timestamp":1638338694,"openIssues":5117},{"timestamp":1638335001,"openIssues":5114,"stars":124730,"closedIssues":119073,"closedPRs":2739,"openPRs":236,"mergedPRs":7810},{"timestamp":1638331666,"openPRs":236,"closedIssues":119073,"openIssues":5112,"stars":124728,"mergedPRs":7810,"closedPRs":2739},{"openIssues":5109,"openPRs":236,"closedPRs":2739,"stars":124728,"closedIssues":119071,"timestamp":1638327801,"mergedPRs":7810},{"openPRs":236,"closedPRs":2739,"mergedPRs":7810,"stars":124723,"timestamp":1638325002,"openIssues":5113,"closedIssues":119065},{"stars":124723,"openPRs":236,"openIssues":5111,"mergedPRs":7810,"closedIssues":119064,"closedPRs":2739,"timestamp":1638321964},{"openPRs":235,"closedIssues":119061,"closedPRs":2739,"mergedPRs":7810,"openIssues":5112,"stars":124721,"timestamp":1638317200},{"closedIssues":119058,"stars":124721,"mergedPRs":7810,"timestamp":1638313406,"openIssues":5113,"openPRs":235,"closedPRs":2739},{"timestamp":1638309813,"mergedPRs":7810,"openIssues":5110,"closedIssues":119057,"openPRs":235,"closedPRs":2739,"stars":124719},{"stars":124718,"openPRs":235,"openIssues":5111,"closedPRs":2739,"timestamp":1638306201,"closedIssues":119054,"mergedPRs":7810},{"timestamp":1638302595,"closedPRs":2739,"openPRs":234,"closedIssues":119048,"mergedPRs":7810,"openIssues":5113,"stars":124715},{"stars":124712,"closedIssues":119041,"mergedPRs":7810,"closedPRs":2739,"openPRs":234,"timestamp":1638299020,"openIssues":5115},{"openIssues":5115,"closedIssues":119030,"mergedPRs":7810,"closedPRs":2739,"timestamp":1638295458,"openPRs":234,"stars":124713},{"timestamp":1638292334,"openIssues":5112,"closedPRs":2739,"closedIssues":119024,"mergedPRs":7810,"stars":124711,"openPRs":234},{"stars":124712,"closedPRs":2739,"timestamp":1638288378,"closedIssues":119027,"openPRs":234,"mergedPRs":7810,"openIssues":5100},{"openIssues":5100,"timestamp":1638284627,"closedPRs":2739,"mergedPRs":7810,"openPRs":234,"stars":124709,"closedIssues":119019},{"openPRs":234,"timestamp":1638281072,"closedPRs":2739,"mergedPRs":7810,"openIssues":5098,"stars":124707,"closedIssues":119016},{"timestamp":1638277697,"stars":124705,"mergedPRs":7810,"openIssues":5091,"openPRs":234,"closedIssues":119013,"closedPRs":2739},{"openPRs":234,"stars":124702,"mergedPRs":7810,"openIssues":5086,"timestamp":1638273809,"closedIssues":119013,"closedPRs":2739},{"openPRs":234,"mergedPRs":7810,"openIssues":5087,"timestamp":1638270190,"closedIssues":119008,"closedPRs":2739,"stars":124700},{"openIssues":5079,"openPRs":234,"closedPRs":2739,"stars":124698,"timestamp":1638266902,"mergedPRs":7810,"closedIssues":119008},{"openIssues":5074,"timestamp":1638263297,"closedPRs":2739,"mergedPRs":7810,"stars":124698,"openPRs":234,"closedIssues":119007},{"stars":124691,"openPRs":233,"openIssues":5072,"closedPRs":2739,"timestamp":1638259392,"closedIssues":119006,"mergedPRs":7810},{"timestamp":1638255800,"mergedPRs":7810,"openIssues":5071,"stars":124689,"closedIssues":119003,"closedPRs":2739,"openPRs":233},{"mergedPRs":7810,"closedIssues":119003,"timestamp":1638252211,"stars":124688,"openIssues":5067,"openPRs":232,"closedPRs":2739},{"timestamp":1638248587,"closedPRs":2739,"openIssues":5066,"mergedPRs":7810,"closedIssues":119003,"openPRs":232,"stars":124685},{"closedPRs":2739,"timestamp":1638245015,"openPRs":232,"openIssues":5066,"stars":124684,"mergedPRs":7810,"closedIssues":119003},{"mergedPRs":7810,"timestamp":1638241403,"closedPRs":2739,"openPRs":232,"stars":124684,"closedIssues":119002,"openIssues":5064},{"mergedPRs":7810,"timestamp":1638238032,"closedIssues":118997,"closedPRs":2739,"openPRs":232,"openIssues":5067,"stars":124682},{"timestamp":1638235369,"closedPRs":2739,"stars":124680,"openIssues":5067,"closedIssues":118997,"openPRs":232,"mergedPRs":7810},{"closedIssues":118996,"timestamp":1638230768,"openPRs":232,"openIssues":5068,"closedPRs":2739,"stars":124676,"mergedPRs":7810},{"timestamp":1638227016,"openPRs":233,"closedPRs":2739,"mergedPRs":7809,"stars":124678,"closedIssues":118989,"openIssues":5071},{"closedIssues":118982,"openPRs":233,"openIssues":5075,"mergedPRs":7809,"closedPRs":2739,"timestamp":1638223400,"stars":124679},{"closedPRs":2739,"openPRs":231,"openIssues":5082,"mergedPRs":7809,"timestamp":1638219791,"stars":124678,"closedIssues":118974},{"closedPRs":2739,"closedIssues":118973,"openIssues":5076,"openPRs":231,"stars":124676,"mergedPRs":7809,"timestamp":1638216222},{"timestamp":1638212593,"mergedPRs":7809,"openPRs":231,"closedIssues":118965,"stars":124676,"openIssues":5081,"closedPRs":2739},{"openIssues":5079,"stars":124674,"openPRs":231,"closedIssues":118962,"closedPRs":2739,"timestamp":1638209019,"mergedPRs":7809},{"openIssues":5074,"timestamp":1638205950,"closedIssues":118960,"openPRs":231,"closedPRs":2739,"mergedPRs":7809,"stars":124673},{"closedIssues":118954,"openIssues":5075,"mergedPRs":7809,"stars":124671,"timestamp":1638202085,"closedPRs":2739,"openPRs":231},{"closedPRs":2739,"openPRs":231,"timestamp":1638198343,"stars":124669,"mergedPRs":7809,"closedIssues":118948,"openIssues":5077},{"mergedPRs":7809,"openIssues":5074,"closedIssues":118946,"timestamp":1638194900,"openPRs":231,"stars":124668,"closedPRs":2739},{"openPRs":231,"mergedPRs":7809,"closedIssues":118944,"stars":124667,"timestamp":1638191401,"openIssues":5074,"closedPRs":2739},{"mergedPRs":7809,"stars":124664,"timestamp":1638187480,"closedPRs":2738,"openIssues":5069,"openPRs":230,"closedIssues":118943},{"closedPRs":2737,"openIssues":5069,"mergedPRs":7809,"timestamp":1638183804,"closedIssues":118939,"openPRs":230,"stars":124661},{"closedPRs":2735,"closedIssues":118936,"openIssues":5066,"stars":124660,"openPRs":234,"mergedPRs":7807,"timestamp":1638180497},{"openPRs":233,"closedPRs":2735,"closedIssues":118936,"openIssues":5064,"timestamp":1638176891,"mergedPRs":7807,"stars":124659},{"mergedPRs":7807,"stars":124658,"closedPRs":2734,"closedIssues":118922,"openIssues":5074,"timestamp":1638173026,"openPRs":234},{"closedPRs":2734,"stars":124655,"openPRs":234,"openIssues":5075,"timestamp":1638169415,"closedIssues":118921,"mergedPRs":7807},{"openIssues":5076,"openPRs":234,"closedPRs":2734,"closedIssues":118920,"timestamp":1638165809,"mergedPRs":7807,"stars":124654},{"openPRs":234,"closedIssues":118919,"closedPRs":2734,"mergedPRs":7807,"openIssues":5075,"timestamp":1638162203,"stars":124654},{"timestamp":1638158623,"closedPRs":2734,"mergedPRs":7807,"closedIssues":118917,"stars":124654,"openPRs":234,"openIssues":5076},{"closedIssues":118917,"closedPRs":2734,"openIssues":5074,"mergedPRs":7807,"timestamp":1638154998,"openPRs":234,"stars":124652},{"mergedPRs":7807,"openIssues":5074,"timestamp":1638152062,"closedIssues":118915,"closedPRs":2734,"openPRs":234,"stars":124652},{"closedPRs":2734,"closedIssues":118915,"stars":124651,"timestamp":1638149069,"mergedPRs":7807,"openPRs":234,"openIssues":5071},{"openPRs":234,"openIssues":5071,"closedPRs":2734,"mergedPRs":7807,"closedIssues":118914,"timestamp":1638144377,"stars":124649},{"openPRs":234,"openIssues":5071,"timestamp":1638140600,"mergedPRs":7807,"stars":124649,"closedIssues":118914,"closedPRs":2734},{"openIssues":5072,"closedIssues":118912,"timestamp":1638136985,"openPRs":234,"closedPRs":2734,"mergedPRs":7807,"stars":124648},{"closedIssues":118910,"timestamp":1638133392,"closedPRs":2734,"openIssues":5074,"mergedPRs":7807,"stars":124648,"openPRs":234},{"openPRs":234,"stars":124648,"closedIssues":118909,"mergedPRs":7807,"closedPRs":2734,"timestamp":1638129797,"openIssues":5074},{"closedPRs":2734,"openIssues":5073,"mergedPRs":7807,"stars":124647,"timestamp":1638126188,"openPRs":234,"closedIssues":118909},{"closedPRs":2734,"mergedPRs":7807,"stars":124645,"openPRs":234,"timestamp":1638122590,"closedIssues":118909,"openIssues":5071},{"openIssues":5070,"closedPRs":2734,"timestamp":1638119203,"stars":124645,"openPRs":234,"mergedPRs":7807,"closedIssues":118909},{"timestamp":1638115404,"openPRs":234,"closedIssues":118909,"openIssues":5067,"mergedPRs":7807,"closedPRs":2734,"stars":124644},{"timestamp":1638111788,"openPRs":234,"closedIssues":118909,"closedPRs":2734,"stars":124644,"mergedPRs":7807,"openIssues":5067},{"closedPRs":2734,"openPRs":234,"mergedPRs":7807,"timestamp":1638108184,"stars":124643,"openIssues":5066,"closedIssues":118908},{"mergedPRs":7807,"timestamp":1638104781,"stars":124640,"closedIssues":118907,"openPRs":234,"closedPRs":2734,"openIssues":5065},{"stars":124638,"openPRs":234,"closedIssues":118906,"timestamp":1638101022,"mergedPRs":7807,"closedPRs":2734,"openIssues":5066},{"openPRs":234,"mergedPRs":7807,"openIssues":5067,"closedPRs":2734,"timestamp":1638097392,"stars":124637,"closedIssues":118904},{"mergedPRs":7807,"openIssues":5065,"openPRs":234,"closedIssues":118904,"closedPRs":2734,"stars":124637,"timestamp":1638093807},{"timestamp":1638090183,"mergedPRs":7806,"stars":124637,"openPRs":234,"closedIssues":118903,"openIssues":5066,"closedPRs":2733},{"mergedPRs":7806,"stars":124636,"openIssues":5063,"closedIssues":118902,"closedPRs":2733,"openPRs":234,"timestamp":1638086621},{"openPRs":234,"closedIssues":118902,"mergedPRs":7806,"stars":124635,"openIssues":5063,"closedPRs":2733,"timestamp":1638082994},{"closedIssues":118902,"stars":124636,"openIssues":5063,"mergedPRs":7806,"timestamp":1638079400,"closedPRs":2733,"openPRs":234},{"openPRs":234,"openIssues":5062,"mergedPRs":7806,"closedPRs":2733,"stars":124636,"closedIssues":118902,"timestamp":1638075784},{"mergedPRs":7806,"stars":124635,"openIssues":5062,"openPRs":234,"closedPRs":2733,"closedIssues":118902,"timestamp":1638072212},{"closedIssues":118902,"mergedPRs":7806,"openIssues":5060,"stars":124632,"closedPRs":2733,"timestamp":1638068592,"openPRs":234},{"stars":124631,"openIssues":5061,"closedPRs":2733,"closedIssues":118901,"timestamp":1638065604,"mergedPRs":7806,"openPRs":234},{"closedPRs":2733,"stars":124630,"openPRs":234,"openIssues":5062,"timestamp":1638062680,"mergedPRs":7806,"closedIssues":118900},{"mergedPRs":7806,"closedPRs":2733,"closedIssues":118900,"openPRs":234,"stars":124628,"openIssues":5061,"timestamp":1638058036},{"closedIssues":118900,"timestamp":1638055629,"closedPRs":2733,"stars":124626,"openIssues":5061,"openPRs":234,"mergedPRs":7806},{"closedIssues":118900,"openIssues":5059,"openPRs":234,"closedPRs":2733,"stars":124625,"timestamp":1638043397,"mergedPRs":7806},{"openPRs":234,"closedPRs":2733,"closedIssues":118900,"timestamp":1638039785,"mergedPRs":7806,"stars":124624,"openIssues":5057},{"openPRs":235,"stars":124624,"closedPRs":2733,"mergedPRs":7805,"closedIssues":118899,"openIssues":5058,"timestamp":1638036199},{"openPRs":235,"closedIssues":118897,"timestamp":1638032801,"stars":124623,"mergedPRs":7805,"openIssues":5059,"closedPRs":2733},{"stars":124620,"closedPRs":2733,"mergedPRs":7805,"timestamp":1638029004,"closedIssues":118898,"openIssues":5057,"openPRs":235},{"stars":124615,"openPRs":235,"closedPRs":2733,"openIssues":5055,"timestamp":1638025386,"closedIssues":118898,"mergedPRs":7805},{"closedIssues":118897,"openPRs":235,"mergedPRs":7805,"timestamp":1638021798,"stars":124612,"openIssues":5055,"closedPRs":2733},{"closedIssues":118897,"mergedPRs":7805,"stars":124609,"timestamp":1638018403,"openIssues":5054,"closedPRs":2733,"openPRs":235},{"closedPRs":2733,"openPRs":234,"timestamp":1638014623,"closedIssues":118895,"mergedPRs":7805,"stars":124606,"openIssues":5053},{"openIssues":5055,"timestamp":1638011064,"closedIssues":118892,"openPRs":234,"stars":124604,"mergedPRs":7805,"closedPRs":2733},{"closedPRs":2733,"mergedPRs":7805,"closedIssues":118892,"openIssues":5054,"stars":124603,"timestamp":1638007392,"openPRs":233},{"timestamp":1638003787,"openIssues":5054,"closedPRs":2733,"stars":124601,"mergedPRs":7805,"openPRs":233,"closedIssues":118892},{"stars":124600,"openIssues":5054,"mergedPRs":7805,"openPRs":233,"timestamp":1638000193,"closedIssues":118889,"closedPRs":2733},{"openIssues":5054,"timestamp":1637996608,"stars":124596,"closedIssues":118889,"mergedPRs":7805,"closedPRs":2733,"openPRs":232},{"closedIssues":118889,"timestamp":1637993023,"openPRs":232,"closedPRs":2733,"openIssues":5053,"mergedPRs":7805,"stars":124593},{"stars":124590,"openIssues":5052,"mergedPRs":7805,"closedIssues":118889,"timestamp":1637989392,"closedPRs":2733,"openPRs":232},{"stars":124590,"closedIssues":118889,"mergedPRs":7805,"timestamp":1637985809,"openPRs":232,"closedPRs":2733,"openIssues":5052},{"openPRs":232,"closedIssues":118889,"timestamp":1637982183,"stars":124590,"mergedPRs":7805,"openIssues":5051,"closedPRs":2733},{"openPRs":232,"closedIssues":118881,"stars":124588,"openIssues":5056,"closedPRs":2733,"timestamp":1637979254,"mergedPRs":7805},{"mergedPRs":7805,"closedPRs":2733,"openPRs":231,"openIssues":5057,"closedIssues":118880,"stars":124586,"timestamp":1637976258},{"stars":124586,"timestamp":1637971547,"closedPRs":2733,"mergedPRs":7805,"openPRs":231,"openIssues":5057,"closedIssues":118879},{"closedPRs":2733,"timestamp":1637967800,"mergedPRs":7805,"openPRs":231,"closedIssues":118878,"stars":124584,"openIssues":5057},{"openIssues":5057,"stars":124583,"closedPRs":2733,"openPRs":231,"timestamp":1637964207,"mergedPRs":7805,"closedIssues":118878},{"timestamp":1637960608,"mergedPRs":7805,"openIssues":5056,"stars":124580,"openPRs":231,"closedIssues":118878,"closedPRs":2733},{"openIssues":5054,"mergedPRs":7805,"stars":124579,"openPRs":231,"closedIssues":118878,"closedPRs":2733,"timestamp":1637957011},{"mergedPRs":7805,"closedPRs":2733,"openIssues":5052,"stars":124577,"timestamp":1637953408,"openPRs":231,"closedIssues":118878},{"closedPRs":2733,"openPRs":231,"timestamp":1637949799,"mergedPRs":7805,"openIssues":5052,"closedIssues":118877,"stars":124574},{"stars":124572,"openPRs":231,"mergedPRs":7805,"closedIssues":118877,"openIssues":5049,"closedPRs":2733,"timestamp":1637946445},{"openPRs":231,"closedPRs":2733,"timestamp":1637942617,"openIssues":5050,"mergedPRs":7805,"closedIssues":118876,"stars":124569},{"mergedPRs":7805,"openPRs":231,"timestamp":1637939025,"stars":124568,"closedPRs":2733,"openIssues":5051,"closedIssues":118872},{"closedIssues":118871,"mergedPRs":7805,"openPRs":230,"stars":124567,"timestamp":1637935400,"closedPRs":2733,"openIssues":5048},{"mergedPRs":7805,"stars":124563,"closedPRs":2733,"closedIssues":118870,"timestamp":1637932046,"openIssues":5046,"openPRs":229},{"timestamp":1637928230,"openPRs":229,"stars":124561,"closedIssues":118869,"closedPRs":2733,"mergedPRs":7805,"openIssues":5043},{"stars":124559,"openIssues":5046,"mergedPRs":7805,"timestamp":1637924578,"openPRs":229,"closedPRs":2733,"closedIssues":118863},{"closedPRs":2733,"openIssues":5042,"timestamp":1637920987,"closedIssues":118863,"stars":124560,"mergedPRs":7803,"openPRs":231},{"mergedPRs":7802,"openPRs":231,"openIssues":5045,"closedIssues":118857,"stars":124561,"closedPRs":2733,"timestamp":1637917694},{"closedIssues":118854,"stars":124560,"openIssues":5047,"timestamp":1637913819,"closedPRs":2733,"mergedPRs":7802,"openPRs":231},{"openPRs":231,"closedIssues":118854,"stars":124560,"closedPRs":2733,"mergedPRs":7802,"openIssues":5044,"timestamp":1637910188},{"stars":124557,"mergedPRs":7802,"openPRs":231,"closedPRs":2733,"openIssues":5041,"closedIssues":118853,"timestamp":1637906600},{"timestamp":1637902986,"stars":124556,"openIssues":5038,"openPRs":231,"closedIssues":118852,"closedPRs":2733,"mergedPRs":7802},{"openPRs":231,"stars":124554,"closedIssues":118852,"timestamp":1637899395,"openIssues":5036,"mergedPRs":7802,"closedPRs":2733},{"timestamp":1637895804,"openPRs":231,"closedIssues":118852,"stars":124554,"closedPRs":2733,"openIssues":5033,"mergedPRs":7802},{"closedPRs":2733,"stars":124551,"openIssues":5033,"timestamp":1637892797,"mergedPRs":7802,"openPRs":231,"closedIssues":118852},{"openPRs":231,"closedPRs":2733,"closedIssues":118852,"stars":124550,"mergedPRs":7802,"timestamp":1637889825,"openIssues":5033},{"closedPRs":2733,"openPRs":231,"closedIssues":118852,"stars":124549,"openIssues":5031,"mergedPRs":7802,"timestamp":1637885176},{"openPRs":232,"mergedPRs":7801,"openIssues":5031,"stars":124549,"closedIssues":118851,"closedPRs":2733,"timestamp":1637881418},{"mergedPRs":7801,"stars":124548,"openPRs":232,"closedPRs":2733,"closedIssues":118850,"openIssues":5032,"timestamp":1637877809},{"mergedPRs":7801,"openPRs":232,"closedIssues":118850,"closedPRs":2733,"timestamp":1637874205,"openIssues":5032,"stars":124544},{"closedPRs":2733,"stars":124543,"timestamp":1637870611,"openPRs":232,"closedIssues":118850,"mergedPRs":7801,"openIssues":5030},{"mergedPRs":7801,"openIssues":5027,"closedIssues":118850,"stars":124542,"timestamp":1637866992,"openPRs":232,"closedPRs":2733},{"timestamp":1637863411,"openPRs":231,"closedIssues":118849,"closedPRs":2733,"mergedPRs":7801,"stars":124540,"openIssues":5026},{"openPRs":231,"closedPRs":2733,"closedIssues":118848,"mergedPRs":7801,"timestamp":1637860051,"openIssues":5023,"stars":124539},{"closedIssues":118845,"openPRs":231,"mergedPRs":7801,"openIssues":5025,"closedPRs":2733,"stars":124538,"timestamp":1637856206},{"timestamp":1637852595,"closedIssues":118844,"closedPRs":2733,"stars":124537,"openPRs":230,"mergedPRs":7801,"openIssues":5024},{"closedIssues":118844,"closedPRs":2732,"stars":124533,"openIssues":5020,"openPRs":231,"timestamp":1637849024,"mergedPRs":7801},{"closedPRs":2732,"timestamp":1637845650,"openPRs":231,"stars":124530,"closedIssues":118840,"mergedPRs":7800,"openIssues":5022},{"closedPRs":2732,"timestamp":1637841818,"closedIssues":118837,"stars":124526,"openIssues":5017,"openPRs":231,"mergedPRs":7800},{"closedPRs":2732,"stars":124525,"openIssues":5022,"timestamp":1637838488,"closedIssues":118829,"openPRs":231,"mergedPRs":7800},{"closedPRs":2732,"timestamp":1637834607,"mergedPRs":7800,"stars":124520,"openIssues":5017,"closedIssues":118828,"openPRs":230},{"mergedPRs":7800,"stars":124518,"openIssues":5015,"timestamp":1637831291,"closedIssues":118825,"openPRs":230,"closedPRs":2732},{"closedPRs":2731,"closedIssues":118823,"mergedPRs":7800,"stars":124513,"timestamp":1637827420,"openIssues":5013,"openPRs":230},{"closedIssues":118822,"closedPRs":2731,"mergedPRs":7800,"openIssues":5011,"timestamp":1637824110,"openPRs":230,"stars":124514},{"closedPRs":2731,"stars":124514,"mergedPRs":7800,"openIssues":5009,"closedIssues":118821,"openPRs":230,"timestamp":1637820204},{"mergedPRs":7800,"openPRs":230,"closedPRs":2731,"timestamp":1637816628,"closedIssues":118820,"openIssues":5010,"stars":124512},{"openPRs":230,"closedIssues":118820,"openIssues":5008,"mergedPRs":7800,"timestamp":1637813003,"closedPRs":2731,"stars":124511},{"openPRs":230,"openIssues":5006,"timestamp":1637809404,"stars":124510,"closedIssues":118819,"closedPRs":2731,"mergedPRs":7800},{"openPRs":230,"closedIssues":118819,"closedPRs":2731,"stars":124504,"timestamp":1637806478,"openIssues":5005,"mergedPRs":7800},{"timestamp":1637803468,"closedIssues":118819,"mergedPRs":7800,"stars":124501,"closedPRs":2731,"openIssues":5002,"openPRs":230},{"openPRs":230,"closedPRs":2731,"timestamp":1637798755,"stars":124499,"openIssues":5003,"closedIssues":118817,"mergedPRs":7800},{"stars":124499,"openPRs":230,"timestamp":1637794999,"openIssues":4998,"closedIssues":118816,"mergedPRs":7800,"closedPRs":2731},{"openIssues":4998,"closedIssues":118814,"timestamp":1637791409,"openPRs":230,"closedPRs":2731,"mergedPRs":7800,"stars":124497},{"timestamp":1637787795,"mergedPRs":7800,"openPRs":230,"closedPRs":2731,"openIssues":4998,"stars":124495,"closedIssues":118810},{"mergedPRs":7800,"closedPRs":2731,"timestamp":1637784206,"stars":124493,"openIssues":4995,"closedIssues":118811,"openPRs":229},{"timestamp":1637780697,"stars":124493,"closedPRs":2731,"closedIssues":118807,"openIssues":4995,"openPRs":229,"mergedPRs":7799},{"mergedPRs":7799,"openIssues":4996,"openPRs":229,"stars":124492,"closedIssues":118804,"closedPRs":2731,"timestamp":1637776995},{"timestamp":1637773741,"closedPRs":2731,"stars":124492,"mergedPRs":7797,"closedIssues":118800,"openIssues":4999,"openPRs":231},{"openPRs":229,"openIssues":5001,"timestamp":1637770107,"closedIssues":118797,"mergedPRs":7797,"stars":124491,"closedPRs":2731},{"closedPRs":2730,"mergedPRs":7796,"stars":124488,"timestamp":1637766230,"closedIssues":118795,"openIssues":5000,"openPRs":230},{"stars":124486,"closedIssues":118794,"openPRs":229,"timestamp":1637762619,"openIssues":4997,"closedPRs":2730,"mergedPRs":7796},{"mergedPRs":7796,"closedIssues":118791,"timestamp":1637759544,"openPRs":229,"stars":124486,"openIssues":4992,"closedPRs":2730},{"timestamp":1637755705,"mergedPRs":7794,"openIssues":4995,"stars":124482,"closedPRs":2730,"closedIssues":118787,"openPRs":230},{"closedIssues":118770,"mergedPRs":7794,"openPRs":230,"timestamp":1637752089,"stars":124481,"openIssues":5010,"closedPRs":2730},{"closedPRs":2730,"timestamp":1637748498,"openIssues":5010,"openPRs":230,"closedIssues":118769,"mergedPRs":7794,"stars":124481},{"openPRs":230,"openIssues":5009,"closedIssues":118767,"stars":124477,"mergedPRs":7794,"timestamp":1637744905,"closedPRs":2730},{"stars":124474,"closedIssues":118763,"openIssues":5010,"closedPRs":2730,"mergedPRs":7794,"timestamp":1637741018,"openPRs":230},{"closedPRs":2730,"mergedPRs":7794,"stars":124472,"closedIssues":118761,"timestamp":1637737397,"openPRs":230,"openIssues":5011},{"openIssues":5012,"closedIssues":118758,"closedPRs":2730,"openPRs":230,"mergedPRs":7794,"stars":124470,"timestamp":1637733812},{"mergedPRs":7794,"openPRs":230,"closedPRs":2730,"openIssues":5013,"stars":124470,"timestamp":1637730188,"closedIssues":118756},{"closedPRs":2730,"timestamp":1637726607,"openPRs":230,"mergedPRs":7794,"stars":124466,"closedIssues":118756,"openIssues":5013},{"closedPRs":2730,"mergedPRs":7794,"closedIssues":118754,"openPRs":230,"timestamp":1637722998,"openIssues":5012,"stars":124463},{"closedPRs":2730,"stars":124461,"timestamp":1637720016,"openPRs":230,"closedIssues":118750,"mergedPRs":7794,"openIssues":5014},{"closedPRs":2730,"openIssues":5012,"timestamp":1637717052,"stars":124459,"mergedPRs":7794,"closedIssues":118750,"openPRs":230},{"openPRs":229,"stars":124457,"mergedPRs":7794,"timestamp":1637712371,"closedIssues":118748,"openIssues":5011,"closedPRs":2730},{"openPRs":228,"closedIssues":118745,"stars":124458,"mergedPRs":7794,"closedPRs":2730,"openIssues":5013,"timestamp":1637708596},{"closedPRs":2729,"timestamp":1637705011,"stars":124456,"closedIssues":118744,"mergedPRs":7792,"openPRs":229,"openIssues":5011},{"openIssues":5009,"stars":124453,"timestamp":1637701403,"closedIssues":118741,"openPRs":228,"closedPRs":2729,"mergedPRs":7792},{"timestamp":1637697811,"closedIssues":118741,"openPRs":228,"mergedPRs":7792,"openIssues":5007,"closedPRs":2729,"stars":124453},{"closedIssues":118736,"timestamp":1637694186,"stars":124453,"openIssues":5009,"closedPRs":2729,"openPRs":228,"mergedPRs":7791},{"closedIssues":118735,"mergedPRs":7790,"stars":124449,"openPRs":229,"closedPRs":2729,"openIssues":5005,"timestamp":1637690642},{"closedIssues":118735,"stars":124448,"timestamp":1637687494,"closedPRs":2729,"mergedPRs":7790,"openPRs":229,"openIssues":5001},{"closedIssues":118731,"stars":124448,"openPRs":229,"closedPRs":2729,"mergedPRs":7789,"openIssues":5001,"timestamp":1637683712},{"openPRs":227,"openIssues":4995,"mergedPRs":7789,"closedIssues":118727,"timestamp":1637679804,"closedPRs":2729,"stars":124448},{"mergedPRs":7789,"timestamp":1637676421,"openIssues":4997,"closedPRs":2729,"openPRs":227,"closedIssues":118724,"stars":124444},{"openIssues":4996,"closedPRs":2729,"mergedPRs":7789,"timestamp":1637673157,"openPRs":227,"stars":124442,"closedIssues":118724},{"closedIssues":118724,"mergedPRs":7789,"stars":124439,"timestamp":1637669294,"openPRs":227,"openIssues":4993,"closedPRs":2729},{"closedPRs":2729,"closedIssues":118705,"timestamp":1637665473,"openPRs":227,"openIssues":5010,"mergedPRs":7789,"stars":124436},{"mergedPRs":7788,"timestamp":1637662123,"openIssues":5013,"stars":124434,"openPRs":228,"closedPRs":2729,"closedIssues":118699},{"openPRs":228,"timestamp":1637658217,"closedPRs":2729,"openIssues":5012,"mergedPRs":7788,"stars":124432,"closedIssues":118697},{"mergedPRs":7788,"timestamp":1637654611,"closedPRs":2729,"openIssues":5012,"stars":124429,"openPRs":228,"closedIssues":118694},{"closedPRs":2729,"closedIssues":118693,"openPRs":228,"openIssues":5011,"timestamp":1637650995,"mergedPRs":7788,"stars":124425},{"openPRs":228,"mergedPRs":7788,"closedPRs":2729,"stars":124421,"openIssues":5009,"timestamp":1637647402,"closedIssues":118693},{"timestamp":1637643787,"openPRs":228,"closedIssues":118693,"mergedPRs":7788,"stars":124417,"closedPRs":2729,"openIssues":5008},{"openPRs":228,"mergedPRs":7788,"closedIssues":118693,"closedPRs":2729,"timestamp":1637640218,"openIssues":5007,"stars":124417},{"stars":124414,"timestamp":1637636599,"openIssues":5005,"closedIssues":118693,"openPRs":228,"mergedPRs":7788,"closedPRs":2729},{"openPRs":228,"mergedPRs":7787,"openIssues":5006,"stars":124412,"timestamp":1637633600,"closedPRs":2729,"closedIssues":118689},{"closedPRs":2729,"openIssues":5005,"closedIssues":118688,"openPRs":228,"mergedPRs":7787,"stars":124407,"timestamp":1637630654},{"mergedPRs":7787,"openPRs":228,"timestamp":1637625963,"openIssues":5005,"closedIssues":118686,"closedPRs":2729,"stars":124405},{"timestamp":1637622189,"mergedPRs":7787,"closedPRs":2729,"stars":124403,"openIssues":5004,"openPRs":228,"closedIssues":118686},{"stars":124400,"timestamp":1637618613,"openIssues":5004,"closedIssues":118684,"mergedPRs":7787,"openPRs":229,"closedPRs":2728},{"timestamp":1637615025,"mergedPRs":7786,"stars":124398,"openIssues":5001,"closedPRs":2728,"openPRs":230,"closedIssues":118682},{"mergedPRs":7785,"timestamp":1637611393,"openPRs":231,"closedPRs":2728,"stars":124398,"openIssues":5008,"closedIssues":118672},{"timestamp":1637608107,"closedPRs":2728,"openPRs":230,"stars":124397,"openIssues":5009,"closedIssues":118669,"mergedPRs":7785},{"closedPRs":2728,"closedIssues":118667,"stars":124392,"openPRs":229,"mergedPRs":7784,"openIssues":5007,"timestamp":1637604518},{"timestamp":1637601194,"closedIssues":118665,"openIssues":5007,"mergedPRs":7784,"openPRs":228,"closedPRs":2728,"stars":124389},{"openPRs":227,"mergedPRs":7784,"closedPRs":2728,"timestamp":1637597309,"openIssues":5008,"closedIssues":118661,"stars":124387},{"openPRs":228,"closedIssues":118658,"stars":124386,"timestamp":1637593734,"mergedPRs":7782,"closedPRs":2728,"openIssues":5010},{"mergedPRs":7782,"timestamp":1637589818,"openPRs":226,"closedIssues":118651,"stars":124383,"closedPRs":2728,"openIssues":5012},{"closedPRs":2728,"closedIssues":118650,"mergedPRs":7782,"timestamp":1637586479,"openPRs":225,"stars":124381,"openIssues":5011},{"closedIssues":118647,"openIssues":5010,"stars":124379,"mergedPRs":7782,"closedPRs":2728,"timestamp":1637582910,"openPRs":225},{"timestamp":1637579301,"mergedPRs":7782,"closedPRs":2728,"stars":124379,"closedIssues":118642,"openPRs":225,"openIssues":5015},{"closedPRs":2728,"timestamp":1637575713,"openPRs":225,"mergedPRs":7782,"stars":124377,"openIssues":5015,"closedIssues":118641},{"closedIssues":118640,"closedPRs":2728,"stars":124374,"timestamp":1637572094,"openPRs":225,"openIssues":5015,"mergedPRs":7782},{"timestamp":1637568218,"openIssues":5014,"stars":124373,"closedIssues":118640,"openPRs":225,"closedPRs":2728,"mergedPRs":7782},{"mergedPRs":7782,"closedIssues":118636,"timestamp":1637564598,"closedPRs":2728,"openPRs":225,"stars":124372,"openIssues":5019},{"stars":124371,"closedPRs":2728,"closedIssues":118636,"openIssues":5016,"timestamp":1637561016,"mergedPRs":7782,"openPRs":225},{"openIssues":5015,"closedPRs":2728,"closedIssues":118636,"mergedPRs":7782,"timestamp":1637557397,"openPRs":225,"stars":124371},{"timestamp":1637553805,"openIssues":5014,"openPRs":225,"closedPRs":2728,"mergedPRs":7782,"stars":124372,"closedIssues":118636},{"mergedPRs":7782,"timestamp":1637550193,"openPRs":225,"stars":124369,"closedIssues":118633,"openIssues":5017,"closedPRs":2728},{"closedPRs":2727,"openIssues":5017,"mergedPRs":7782,"openPRs":226,"closedIssues":118631,"stars":124368,"timestamp":1637547268},{"mergedPRs":7782,"openIssues":5016,"stars":124367,"closedIssues":118631,"openPRs":226,"timestamp":1637544263,"closedPRs":2727},{"openPRs":226,"stars":124366,"closedIssues":118631,"mergedPRs":7782,"timestamp":1637539573,"openIssues":5016,"closedPRs":2727},{"closedPRs":2727,"closedIssues":118630,"openIssues":5016,"mergedPRs":7782,"timestamp":1637535815,"openPRs":226,"stars":124364},{"closedPRs":2726,"mergedPRs":7782,"stars":124365,"closedIssues":118622,"openPRs":226,"timestamp":1637532199,"openIssues":5022},{"closedIssues":118621,"stars":124363,"openIssues":5022,"mergedPRs":7782,"timestamp":1637528592,"closedPRs":2726,"openPRs":226},{"closedPRs":2726,"timestamp":1637524994,"mergedPRs":7782,"openPRs":225,"openIssues":5022,"stars":124363,"closedIssues":118621},{"openPRs":225,"closedPRs":2726,"timestamp":1637521386,"closedIssues":118620,"mergedPRs":7782,"openIssues":5022,"stars":124363},{"closedPRs":2726,"closedIssues":118619,"mergedPRs":7782,"timestamp":1637517790,"openPRs":225,"stars":124363,"openIssues":5021},{"mergedPRs":7782,"stars":124361,"openIssues":5026,"openPRs":225,"closedIssues":118612,"closedPRs":2726,"timestamp":1637514404},{"openPRs":225,"mergedPRs":7782,"stars":124356,"closedIssues":118612,"closedPRs":2726,"openIssues":5024,"timestamp":1637510605},{"mergedPRs":7782,"openPRs":224,"closedPRs":2726,"timestamp":1637506984,"closedIssues":118610,"stars":124355,"openIssues":5025},{"mergedPRs":7782,"closedPRs":2726,"openIssues":5025,"closedIssues":118610,"openPRs":224,"stars":124356,"timestamp":1637503412},{"openPRs":225,"closedPRs":2725,"closedIssues":118610,"timestamp":1637500008,"openIssues":5022,"stars":124355,"mergedPRs":7782},{"stars":124354,"openPRs":225,"timestamp":1637496228,"openIssues":5021,"closedPRs":2725,"mergedPRs":7782,"closedIssues":118610},{"openPRs":225,"openIssues":5018,"closedPRs":2725,"stars":124352,"closedIssues":118609,"mergedPRs":7782,"timestamp":1637492594},{"openPRs":225,"closedIssues":118610,"openIssues":5015,"timestamp":1637489004,"stars":124352,"mergedPRs":7782,"closedPRs":2725},{"timestamp":1637485394,"closedPRs":2725,"mergedPRs":7782,"openIssues":5014,"closedIssues":118610,"stars":124351,"openPRs":225},{"stars":124348,"closedIssues":118610,"closedPRs":2725,"mergedPRs":7782,"openIssues":5013,"timestamp":1637481822,"openPRs":225},{"openPRs":225,"openIssues":5009,"timestamp":1637478191,"stars":124343,"closedIssues":118610,"mergedPRs":7782,"closedPRs":2725},{"closedPRs":2725,"timestamp":1637474601,"openPRs":225,"closedIssues":118610,"stars":124343,"openIssues":5008,"mergedPRs":7782},{"stars":124344,"mergedPRs":7782,"openPRs":225,"closedPRs":2725,"timestamp":1637470991,"closedIssues":118610,"openIssues":5008},{"closedIssues":118610,"openIssues":5004,"timestamp":1637467405,"stars":124342,"mergedPRs":7782,"openPRs":225,"closedPRs":2725},{"timestamp":1637463786,"openIssues":5004,"openPRs":225,"mergedPRs":7782,"stars":124339,"closedPRs":2725,"closedIssues":118608},{"mergedPRs":7782,"timestamp":1637460883,"closedPRs":2725,"openIssues":5009,"closedIssues":118603,"stars":124340,"openPRs":225},{"openPRs":225,"closedIssues":118602,"closedPRs":2725,"timestamp":1637457908,"stars":124340,"openIssues":5009,"mergedPRs":7780},{"timestamp":1637453175,"openIssues":5009,"mergedPRs":7780,"stars":124339,"closedIssues":118602,"openPRs":225,"closedPRs":2725},{"mergedPRs":7780,"openPRs":226,"closedPRs":2724,"stars":124339,"closedIssues":118601,"timestamp":1637449401,"openIssues":5009},{"closedIssues":118601,"openIssues":5009,"openPRs":226,"stars":124335,"mergedPRs":7780,"timestamp":1637445809,"closedPRs":2724},{"openIssues":5007,"timestamp":1637442193,"closedIssues":118601,"stars":124334,"openPRs":226,"closedPRs":2724,"mergedPRs":7780},{"openIssues":5008,"closedIssues":118600,"stars":124334,"closedPRs":2724,"timestamp":1637438617,"openPRs":226,"mergedPRs":7780},{"openPRs":226,"closedPRs":2724,"mergedPRs":7780,"stars":124331,"timestamp":1637434988,"openIssues":5010,"closedIssues":118598},{"closedPRs":2724,"timestamp":1637431401,"openPRs":226,"stars":124329,"closedIssues":118598,"mergedPRs":7780,"openIssues":5010},{"timestamp":1637427997,"openPRs":226,"closedIssues":118597,"openIssues":5008,"mergedPRs":7780,"closedPRs":2724,"stars":124328},{"openPRs":226,"closedPRs":2724,"openIssues":5006,"stars":124323,"closedIssues":118597,"mergedPRs":7779,"timestamp":1637424198},{"closedIssues":118596,"openIssues":5004,"timestamp":1637420598,"openPRs":226,"mergedPRs":7779,"closedPRs":2724,"stars":124322},{"openIssues":5004,"mergedPRs":7779,"stars":124321,"timestamp":1637417000,"closedIssues":118596,"closedPRs":2724,"openPRs":226},{"timestamp":1637413593,"closedPRs":2724,"openIssues":5004,"stars":124321,"openPRs":226,"mergedPRs":7779,"closedIssues":118596},{"closedIssues":118595,"stars":124319,"mergedPRs":7778,"timestamp":1637409821,"openIssues":5003,"openPRs":227,"closedPRs":2724},{"closedIssues":118593,"openPRs":227,"openIssues":5005,"closedPRs":2724,"mergedPRs":7778,"stars":124319,"timestamp":1637406201},{"mergedPRs":7778,"stars":124318,"closedIssues":118593,"timestamp":1637402607,"openPRs":228,"closedPRs":2723,"openIssues":5005},{"closedIssues":118593,"closedPRs":2723,"stars":124318,"timestamp":1637399052,"openPRs":228,"mergedPRs":7778,"openIssues":5005},{"closedIssues":118593,"closedPRs":2723,"openPRs":227,"stars":124317,"timestamp":1637395609,"mergedPRs":7778,"openIssues":5003},{"openPRs":227,"openIssues":5002,"closedIssues":118593,"closedPRs":2723,"stars":124314,"mergedPRs":7778,"timestamp":1637391815}]
