[{"closedIssues":128714,"openIssues":6406,"timestamp":1654725803,"closedPRs":3004,"openPRs":287,"stars":132614,"mergedPRs":9311},{"timestamp":1654722208,"openIssues":6404,"mergedPRs":9308,"closedPRs":3004,"openPRs":288,"stars":132609,"closedIssues":128711},{"openPRs":286,"closedIssues":128709,"mergedPRs":9307,"stars":132608,"closedPRs":3003,"timestamp":1654718615,"openIssues":6403},{"timestamp":1654714996,"openPRs":287,"closedPRs":3003,"closedIssues":128705,"stars":132607,"openIssues":6404,"mergedPRs":9304},{"stars":132606,"closedPRs":3003,"closedIssues":128702,"timestamp":1654711406,"openIssues":6405,"openPRs":288,"mergedPRs":9301},{"mergedPRs":9299,"timestamp":1654708061,"closedIssues":128696,"closedPRs":3002,"openIssues":6407,"openPRs":289,"stars":132603},{"openPRs":292,"mergedPRs":9295,"closedIssues":128692,"closedPRs":3001,"stars":132603,"openIssues":6408,"timestamp":1654704204},{"openPRs":292,"timestamp":1654700610,"closedIssues":128688,"openIssues":6406,"closedPRs":3000,"stars":132601,"mergedPRs":9293},{"openIssues":6407,"openPRs":293,"mergedPRs":9291,"timestamp":1654697012,"closedIssues":128682,"closedPRs":3000,"stars":132600},{"mergedPRs":9290,"stars":132599,"closedIssues":128681,"timestamp":1654694106,"closedPRs":3000,"openIssues":6404,"openPRs":292},{"openIssues":6408,"openPRs":293,"closedPRs":3000,"mergedPRs":9288,"stars":132595,"timestamp":1654689844,"closedIssues":128676},{"stars":132594,"closedIssues":128661,"mergedPRs":9287,"openPRs":293,"timestamp":1654686486,"openIssues":6419,"closedPRs":3000},{"mergedPRs":9287,"openIssues":6418,"openPRs":292,"timestamp":1654682888,"closedIssues":128660,"stars":132593,"closedPRs":2999},{"openPRs":293,"closedPRs":2999,"stars":132590,"mergedPRs":9286,"openIssues":6418,"timestamp":1654679012,"closedIssues":128658},{"openPRs":294,"closedPRs":2999,"openIssues":6416,"timestamp":1654675406,"mergedPRs":9284,"closedIssues":128657,"stars":132588},{"openPRs":295,"stars":132585,"closedIssues":128655,"mergedPRs":9283,"openIssues":6417,"closedPRs":2999,"timestamp":1654671802},{"openIssues":6416,"closedIssues":128653,"stars":132583,"openPRs":295,"timestamp":1654668208,"closedPRs":2999,"mergedPRs":9281},{"stars":132581,"timestamp":1654664638,"mergedPRs":9281,"closedIssues":128651,"closedPRs":2999,"openIssues":6416,"openPRs":295},{"mergedPRs":9281,"closedPRs":2999,"closedIssues":128651,"timestamp":1654661479,"openPRs":294,"stars":132579,"openIssues":6415},{"stars":132578,"closedPRs":2999,"openIssues":6415,"closedIssues":128651,"timestamp":1654658994,"openPRs":294,"mergedPRs":9281},{"mergedPRs":9281,"stars":132577,"openPRs":294,"closedIssues":128650,"closedPRs":2998,"timestamp":1654656076,"openIssues":6414},{"mergedPRs":9281,"timestamp":1654651903,"closedPRs":2998,"openPRs":293,"closedIssues":128649,"stars":132575,"openIssues":6414},{"stars":132572,"timestamp":1654646924,"openPRs":295,"mergedPRs":9278,"closedIssues":128645,"openIssues":6417,"closedPRs":2998},{"openIssues":6415,"closedIssues":128645,"stars":132571,"openPRs":293,"closedPRs":2998,"mergedPRs":9277,"timestamp":1654642997},{"mergedPRs":9276,"openPRs":293,"openIssues":6412,"closedIssues":128643,"timestamp":1654639399,"closedPRs":2998,"stars":132568},{"openIssues":6414,"stars":132569,"closedPRs":2998,"openPRs":294,"closedIssues":128641,"mergedPRs":9274,"timestamp":1654635799},{"openPRs":295,"timestamp":1654632249,"stars":132568,"closedPRs":2998,"mergedPRs":9272,"closedIssues":128636,"openIssues":6414},{"closedPRs":2998,"timestamp":1654628595,"closedIssues":128633,"mergedPRs":9270,"openIssues":6415,"openPRs":295,"stars":132568},{"openIssues":6417,"closedIssues":128630,"mergedPRs":9267,"timestamp":1654625009,"closedPRs":2998,"stars":132566,"openPRs":297},{"openPRs":296,"openIssues":6417,"closedPRs":2997,"stars":132565,"timestamp":1654621619,"closedIssues":128628,"mergedPRs":9266},{"closedIssues":128624,"stars":132565,"openIssues":6420,"closedPRs":2995,"mergedPRs":9264,"openPRs":298,"timestamp":1654617822},{"openIssues":6421,"timestamp":1654614481,"closedIssues":128622,"closedPRs":2995,"openPRs":298,"mergedPRs":9263,"stars":132562},{"stars":132560,"closedIssues":128618,"openPRs":299,"timestamp":1654610873,"openIssues":6423,"mergedPRs":9260,"closedPRs":2995},{"closedPRs":2995,"mergedPRs":9259,"timestamp":1654607681,"openIssues":6424,"closedIssues":128614,"stars":132554,"openPRs":299},{"closedIssues":128607,"stars":132552,"closedPRs":2995,"openIssues":6428,"openPRs":303,"timestamp":1654603438,"mergedPRs":9254},{"closedIssues":128599,"timestamp":1654599795,"stars":132551,"mergedPRs":9254,"openIssues":6431,"closedPRs":2995,"openPRs":302},{"openIssues":6433,"closedIssues":128594,"closedPRs":2995,"mergedPRs":9254,"timestamp":1654596211,"openPRs":301,"stars":132549},{"stars":132548,"closedIssues":128590,"openIssues":6435,"closedPRs":2995,"openPRs":303,"mergedPRs":9252,"timestamp":1654592592},{"timestamp":1654589020,"closedIssues":128590,"closedPRs":2995,"openIssues":6431,"openPRs":303,"mergedPRs":9251,"stars":132545},{"mergedPRs":9247,"timestamp":1654585415,"openIssues":6435,"stars":132544,"closedIssues":128582,"closedPRs":2995,"openPRs":303},{"closedIssues":128582,"closedPRs":2995,"openIssues":6434,"mergedPRs":9247,"stars":132543,"openPRs":303,"timestamp":1654581819},{"openIssues":6434,"stars":132541,"closedPRs":2995,"mergedPRs":9247,"closedIssues":128582,"timestamp":1654578196,"openPRs":303},{"timestamp":1654574905,"stars":132541,"openIssues":6434,"mergedPRs":9247,"closedIssues":128582,"closedPRs":2995,"openPRs":303},{"openPRs":303,"openIssues":6433,"stars":132540,"timestamp":1654572406,"closedIssues":128579,"mergedPRs":9247,"closedPRs":2995},{"openIssues":6440,"stars":132538,"mergedPRs":9247,"openPRs":302,"timestamp":1654569431,"closedPRs":2995,"closedIssues":128571},{"mergedPRs":9247,"timestamp":1654565482,"stars":132537,"openIssues":6437,"closedIssues":128570,"closedPRs":2995,"openPRs":299},{"openPRs":300,"mergedPRs":9244,"closedIssues":128569,"openIssues":6436,"closedPRs":2995,"stars":132532,"timestamp":1654560528},{"openPRs":301,"stars":132531,"closedIssues":128569,"timestamp":1654556619,"closedPRs":2995,"openIssues":6435,"mergedPRs":9242},{"openPRs":301,"closedPRs":2995,"stars":132530,"closedIssues":128567,"openIssues":6438,"mergedPRs":9242,"timestamp":1654553062},{"closedPRs":2995,"timestamp":1654549385,"stars":132531,"closedIssues":128566,"mergedPRs":9241,"openIssues":6434,"openPRs":301},{"openPRs":301,"mergedPRs":9241,"closedPRs":2995,"stars":132531,"timestamp":1654545810,"openIssues":6427,"closedIssues":128566},{"stars":132530,"timestamp":1654542256,"mergedPRs":9241,"closedIssues":128564,"openIssues":6427,"closedPRs":2995,"openPRs":300},{"timestamp":1654538607,"closedPRs":2995,"openPRs":299,"closedIssues":128564,"openIssues":6426,"mergedPRs":9241,"stars":132529},{"openPRs":301,"mergedPRs":9239,"closedPRs":2995,"timestamp":1654535188,"stars":132526,"openIssues":6425,"closedIssues":128562},{"openIssues":6422,"mergedPRs":9237,"closedIssues":128561,"closedPRs":2995,"stars":132525,"openPRs":299,"timestamp":1654531396},{"closedIssues":128552,"timestamp":1654527808,"closedPRs":2995,"stars":132523,"openPRs":299,"mergedPRs":9237,"openIssues":6428},{"stars":132519,"mergedPRs":9236,"openIssues":6428,"closedPRs":2995,"timestamp":1654524191,"closedIssues":128547,"openPRs":300},{"closedIssues":128547,"mergedPRs":9236,"timestamp":1654521332,"closedPRs":2995,"openPRs":300,"openIssues":6426,"stars":132516},{"mergedPRs":9236,"closedIssues":128546,"closedPRs":2995,"openIssues":6424,"openPRs":299,"stars":132516,"timestamp":1654517039},{"timestamp":1654513403,"stars":132515,"closedIssues":128536,"mergedPRs":9236,"openIssues":6431,"openPRs":299,"closedPRs":2995},{"openIssues":6427,"closedIssues":128536,"timestamp":1654509822,"stars":132516,"mergedPRs":9236,"closedPRs":2995,"openPRs":298},{"openPRs":298,"timestamp":1654506197,"closedIssues":128536,"closedPRs":2995,"mergedPRs":9236,"openIssues":6425,"stars":132512},{"timestamp":1654502619,"closedPRs":2995,"closedIssues":128535,"openPRs":298,"openIssues":6424,"stars":132511,"mergedPRs":9236},{"openPRs":298,"stars":132510,"timestamp":1654499013,"openIssues":6422,"closedIssues":128534,"closedPRs":2995,"mergedPRs":9236},{"openIssues":6422,"openPRs":298,"stars":132508,"mergedPRs":9236,"closedPRs":2995,"closedIssues":128533,"timestamp":1654495431},{"openIssues":6423,"openPRs":300,"closedIssues":128531,"mergedPRs":9234,"closedPRs":2995,"stars":132502,"timestamp":1654491894},{"openIssues":6421,"mergedPRs":9234,"stars":132499,"timestamp":1654488609,"openPRs":300,"closedIssues":128531,"closedPRs":2995},{"timestamp":1654486051,"openPRs":300,"closedPRs":2995,"openIssues":6419,"stars":132499,"closedIssues":128531,"mergedPRs":9234},{"openPRs":298,"closedIssues":128525,"stars":132499,"timestamp":1654483191,"openIssues":6424,"mergedPRs":9234,"closedPRs":2995},{"openIssues":6422,"closedPRs":2995,"openPRs":298,"mergedPRs":9234,"timestamp":1654479144,"closedIssues":128523,"stars":132493},{"openIssues":6420,"closedIssues":128522,"timestamp":1654474127,"mergedPRs":9234,"closedPRs":2995,"stars":132493,"openPRs":298},{"openPRs":298,"timestamp":1654470203,"closedPRs":2995,"closedIssues":128522,"openIssues":6419,"mergedPRs":9234,"stars":132489},{"timestamp":1654466588,"mergedPRs":9234,"stars":132487,"openIssues":6418,"openPRs":298,"closedIssues":128522,"closedPRs":2995},{"timestamp":1654463030,"closedPRs":2995,"openIssues":6418,"mergedPRs":9234,"stars":132484,"closedIssues":128522,"openPRs":298},{"mergedPRs":9234,"closedPRs":2995,"closedIssues":128522,"timestamp":1654459414,"openIssues":6418,"openPRs":298,"stars":132484},{"closedIssues":128522,"timestamp":1654455796,"stars":132481,"openIssues":6418,"openPRs":298,"mergedPRs":9234,"closedPRs":2995},{"closedPRs":2995,"openIssues":6417,"openPRs":298,"stars":132478,"timestamp":1654452247,"mergedPRs":9234,"closedIssues":128522},{"closedPRs":2995,"openIssues":6416,"mergedPRs":9234,"openPRs":298,"stars":132477,"timestamp":1654448590,"closedIssues":128522},{"openIssues":6416,"openPRs":298,"stars":132474,"timestamp":1654444998,"mergedPRs":9234,"closedIssues":128520,"closedPRs":2995},{"closedIssues":128520,"timestamp":1654441409,"stars":132471,"mergedPRs":9234,"closedPRs":2995,"openPRs":298,"openIssues":6416},{"closedIssues":128520,"stars":132470,"openPRs":298,"mergedPRs":9234,"closedPRs":2995,"timestamp":1654437811,"openIssues":6415},{"openIssues":6414,"closedPRs":2995,"mergedPRs":9234,"stars":132469,"closedIssues":128520,"openPRs":298,"timestamp":1654434450},{"closedIssues":128520,"openPRs":298,"mergedPRs":9234,"closedPRs":2995,"stars":132468,"timestamp":1654430688,"openIssues":6411},{"closedPRs":2995,"closedIssues":128518,"openPRs":298,"mergedPRs":9234,"stars":132465,"openIssues":6412,"timestamp":1654427005},{"stars":132465,"openIssues":6411,"closedPRs":2995,"openPRs":298,"timestamp":1654423383,"closedIssues":128518,"mergedPRs":9234},{"timestamp":1654419800,"closedIssues":128518,"closedPRs":2995,"mergedPRs":9234,"stars":132461,"openPRs":297,"openIssues":6411},{"closedPRs":2995,"openIssues":6409,"closedIssues":128517,"openPRs":297,"timestamp":1654416249,"stars":132459,"mergedPRs":9234},{"closedIssues":128516,"openPRs":297,"stars":132459,"openIssues":6409,"closedPRs":2995,"timestamp":1654412609,"mergedPRs":9234},{"openIssues":6408,"mergedPRs":9234,"closedIssues":128516,"stars":132456,"closedPRs":2995,"timestamp":1654408995,"openPRs":297},{"mergedPRs":9234,"openPRs":297,"timestamp":1654405397,"closedPRs":2995,"openIssues":6408,"closedIssues":128516,"stars":132453},{"closedPRs":2995,"closedIssues":128516,"stars":132451,"timestamp":1654401788,"openPRs":297,"openIssues":6407,"mergedPRs":9234},{"openPRs":297,"mergedPRs":9234,"closedIssues":128516,"timestamp":1654399155,"openIssues":6407,"closedPRs":2995,"stars":132450},{"openPRs":297,"timestamp":1654396655,"openIssues":6411,"closedPRs":2995,"closedIssues":128512,"stars":132449,"mergedPRs":9234},{"stars":132448,"timestamp":1654392755,"closedIssues":128512,"mergedPRs":9234,"openPRs":297,"closedPRs":2995,"openIssues":6411},{"mergedPRs":9234,"timestamp":1654387826,"stars":132448,"closedPRs":2995,"closedIssues":128512,"openIssues":6409,"openPRs":297},{"closedPRs":2995,"mergedPRs":9234,"stars":132448,"closedIssues":128512,"openPRs":297,"timestamp":1654383798,"openIssues":6409},{"closedIssues":128511,"mergedPRs":9234,"timestamp":1654380188,"closedPRs":2995,"openIssues":6409,"stars":132448,"openPRs":297},{"timestamp":1654376623,"closedPRs":2995,"openIssues":6409,"openPRs":297,"stars":132447,"mergedPRs":9234,"closedIssues":128511},{"openIssues":6408,"closedIssues":128511,"mergedPRs":9234,"stars":132447,"closedPRs":2995,"openPRs":297,"timestamp":1654373016},{"closedIssues":128511,"openPRs":297,"openIssues":6407,"closedPRs":2995,"stars":132444,"timestamp":1654369385,"mergedPRs":9234},{"closedIssues":128511,"stars":132443,"openPRs":297,"mergedPRs":9234,"timestamp":1654365790,"openIssues":6405,"closedPRs":2995},{"mergedPRs":9234,"openIssues":6405,"openPRs":297,"stars":132443,"closedIssues":128511,"timestamp":1654362192,"closedPRs":2995},{"timestamp":1654358598,"openPRs":297,"mergedPRs":9234,"closedIssues":128511,"openIssues":6405,"closedPRs":2995,"stars":132438},{"closedPRs":2995,"mergedPRs":9234,"openIssues":6407,"closedIssues":128509,"openPRs":297,"stars":132436,"timestamp":1654355001},{"timestamp":1654351417,"closedIssues":128509,"closedPRs":2995,"openPRs":297,"mergedPRs":9234,"openIssues":6406,"stars":132434},{"closedIssues":128509,"mergedPRs":9234,"stars":132434,"timestamp":1654348026,"openPRs":297,"closedPRs":2995,"openIssues":6406},{"timestamp":1654344246,"openPRs":297,"stars":132434,"closedIssues":128509,"closedPRs":2995,"mergedPRs":9234,"openIssues":6406},{"openIssues":6408,"closedPRs":2995,"timestamp":1654340589,"closedIssues":128503,"mergedPRs":9234,"openPRs":297,"stars":132433},{"openPRs":297,"stars":132430,"closedIssues":128503,"closedPRs":2995,"mergedPRs":9234,"timestamp":1654336990,"openIssues":6407},{"mergedPRs":9234,"stars":132430,"closedIssues":128503,"closedPRs":2995,"openPRs":297,"timestamp":1654333401,"openIssues":6406},{"openIssues":6406,"timestamp":1654329918,"closedPRs":2995,"closedIssues":128503,"stars":132427,"mergedPRs":9234,"openPRs":297},{"closedPRs":2995,"mergedPRs":9234,"stars":132425,"closedIssues":128502,"openPRs":297,"openIssues":6405,"timestamp":1654326200},{"mergedPRs":9234,"stars":132426,"closedPRs":2995,"timestamp":1654322606,"openIssues":6405,"closedIssues":128502,"openPRs":297},{"timestamp":1654318991,"closedPRs":2995,"mergedPRs":9234,"closedIssues":128502,"stars":132424,"openIssues":6404,"openPRs":297},{"closedPRs":2995,"closedIssues":128501,"stars":132426,"mergedPRs":9234,"timestamp":1654315390,"openIssues":6404,"openPRs":297},{"timestamp":1654312842,"openIssues":6404,"stars":132426,"mergedPRs":9234,"openPRs":297,"closedPRs":2995,"closedIssues":128501},{"timestamp":1654310002,"openPRs":297,"stars":132425,"closedIssues":128500,"closedPRs":2995,"mergedPRs":9234,"openIssues":6402},{"openIssues":6402,"closedIssues":128500,"closedPRs":2995,"mergedPRs":9234,"timestamp":1654306284,"openPRs":297,"stars":132425},{"timestamp":1654301366,"stars":132423,"closedPRs":2995,"mergedPRs":9234,"closedIssues":128500,"openIssues":6402,"openPRs":297},{"timestamp":1654297400,"mergedPRs":9234,"closedPRs":2995,"stars":132422,"closedIssues":128500,"openPRs":297,"openIssues":6401},{"closedIssues":128499,"closedPRs":2994,"mergedPRs":9233,"openPRs":298,"openIssues":6400,"timestamp":1654293807,"stars":132422},{"mergedPRs":9232,"openPRs":297,"openIssues":6398,"closedPRs":2994,"timestamp":1654290193,"closedIssues":128500,"stars":132420},{"closedIssues":128500,"openIssues":6397,"mergedPRs":9231,"timestamp":1654286609,"stars":132419,"closedPRs":2994,"openPRs":298},{"timestamp":1654283008,"mergedPRs":9230,"openIssues":6396,"stars":132417,"openPRs":297,"closedPRs":2994,"closedIssues":128495},{"mergedPRs":9230,"openPRs":298,"timestamp":1654279404,"closedIssues":128496,"closedPRs":2993,"openIssues":6393,"stars":132417},{"openPRs":298,"stars":132416,"closedPRs":2992,"closedIssues":128492,"openIssues":6395,"timestamp":1654275921,"mergedPRs":9229},{"timestamp":1654272217,"stars":132412,"openIssues":6393,"openPRs":299,"mergedPRs":9226,"closedIssues":128490,"closedPRs":2992},{"mergedPRs":9224,"stars":132410,"closedIssues":128485,"openPRs":299,"timestamp":1654268599,"closedPRs":2991,"openIssues":6395},{"openPRs":296,"timestamp":1654265000,"closedIssues":128484,"mergedPRs":9224,"stars":132407,"closedPRs":2991,"openIssues":6389},{"timestamp":1654262026,"mergedPRs":9223,"closedIssues":128484,"stars":132405,"openPRs":297,"closedPRs":2991,"openIssues":6389},{"closedPRs":2991,"stars":132401,"timestamp":1654257821,"closedIssues":128480,"openIssues":6392,"openPRs":298,"mergedPRs":9222},{"stars":132401,"openIssues":6407,"mergedPRs":9222,"openPRs":297,"closedIssues":128462,"closedPRs":2991,"timestamp":1654254197},{"stars":132400,"closedPRs":2991,"timestamp":1654250610,"mergedPRs":9221,"openPRs":297,"closedIssues":128460,"openIssues":6407},{"closedPRs":2991,"stars":132399,"closedIssues":128460,"openIssues":6405,"mergedPRs":9221,"openPRs":296,"timestamp":1654247014},{"openIssues":6402,"closedIssues":128459,"closedPRs":2991,"mergedPRs":9221,"openPRs":295,"timestamp":1654243412,"stars":132397},{"openPRs":295,"timestamp":1654239796,"mergedPRs":9221,"closedPRs":2991,"stars":132396,"openIssues":6401,"closedIssues":128456},{"openIssues":6401,"timestamp":1654236201,"closedIssues":128453,"openPRs":297,"closedPRs":2991,"mergedPRs":9219,"stars":132396},{"closedIssues":128452,"openPRs":297,"closedPRs":2991,"openIssues":6402,"mergedPRs":9219,"stars":132396,"timestamp":1654232603},{"openIssues":6401,"closedIssues":128452,"stars":132395,"mergedPRs":9218,"timestamp":1654229020,"openPRs":298,"closedPRs":2991},{"openIssues":6401,"timestamp":1654226589,"openPRs":298,"closedIssues":128452,"mergedPRs":9218,"stars":132394,"closedPRs":2991},{"timestamp":1654223747,"closedIssues":128452,"openPRs":298,"mergedPRs":9218,"stars":132392,"openIssues":6400,"closedPRs":2991},{"closedPRs":2991,"mergedPRs":9218,"timestamp":1654219839,"closedIssues":128452,"openIssues":6400,"openPRs":297,"stars":132389},{"timestamp":1654214918,"closedIssues":128452,"openIssues":6399,"mergedPRs":9218,"closedPRs":2991,"openPRs":296,"stars":132389},{"mergedPRs":9218,"openPRs":296,"timestamp":1654211040,"stars":132389,"closedIssues":128450,"closedPRs":2991,"openIssues":6399},{"mergedPRs":9214,"stars":132389,"timestamp":1654207394,"closedIssues":128444,"openPRs":295,"closedPRs":2991,"openIssues":6397},{"stars":132387,"timestamp":1654203819,"closedIssues":128443,"mergedPRs":9213,"closedPRs":2991,"openPRs":294,"openIssues":6392},{"timestamp":1654200238,"closedPRs":2990,"openIssues":6388,"openPRs":296,"mergedPRs":9212,"stars":132385,"closedIssues":128439},{"mergedPRs":9212,"closedIssues":128440,"stars":132385,"timestamp":1654196660,"openIssues":6383,"openPRs":296,"closedPRs":2990},{"closedIssues":128443,"openIssues":6378,"openPRs":296,"timestamp":1654193001,"mergedPRs":9212,"stars":132383,"closedPRs":2990},{"openIssues":6381,"closedPRs":2990,"closedIssues":128438,"mergedPRs":9209,"stars":132382,"timestamp":1654189816,"openPRs":296},{"openPRs":295,"openIssues":6384,"closedIssues":128428,"stars":132381,"mergedPRs":9206,"closedPRs":2990,"timestamp":1654185797},{"openIssues":6383,"mergedPRs":9204,"closedPRs":2990,"openPRs":293,"stars":132378,"closedIssues":128421,"timestamp":1654182222},{"openIssues":6383,"closedIssues":128414,"mergedPRs":9201,"closedPRs":2990,"stars":132376,"openPRs":293,"timestamp":1654178832},{"closedIssues":128414,"openPRs":293,"stars":132374,"timestamp":1654175866,"mergedPRs":9201,"closedPRs":2990,"openIssues":6378},{"openPRs":295,"closedIssues":128401,"closedPRs":2990,"stars":132373,"timestamp":1654171448,"mergedPRs":9193,"openIssues":6385},{"openPRs":295,"stars":132372,"closedIssues":128391,"mergedPRs":9192,"timestamp":1654167799,"openIssues":6394,"closedPRs":2990},{"stars":132370,"timestamp":1654164213,"openIssues":6396,"mergedPRs":9192,"closedPRs":2990,"openPRs":295,"closedIssues":128385},{"closedPRs":2990,"openIssues":6400,"mergedPRs":9191,"timestamp":1654160615,"closedIssues":128381,"openPRs":294,"stars":132367},{"stars":132367,"mergedPRs":9191,"closedIssues":128378,"openIssues":6398,"timestamp":1654157022,"openPRs":293,"closedPRs":2990},{"closedPRs":2990,"closedIssues":128372,"stars":132367,"mergedPRs":9189,"openIssues":6403,"openPRs":293,"timestamp":1654153439},{"openIssues":6405,"mergedPRs":9188,"timestamp":1654149808,"closedIssues":128369,"openPRs":293,"closedPRs":2990,"stars":132366},{"closedIssues":128367,"mergedPRs":9188,"openIssues":6405,"timestamp":1654146800,"closedPRs":2990,"openPRs":293,"stars":132366},{"closedIssues":128367,"closedPRs":2990,"openPRs":293,"stars":132364,"timestamp":1654143614,"mergedPRs":9188,"openIssues":6404},{"closedPRs":2990,"closedIssues":128367,"timestamp":1654140913,"openIssues":6401,"openPRs":293,"stars":132361,"mergedPRs":9188},{"stars":132360,"openPRs":294,"timestamp":1654138016,"closedIssues":128364,"openIssues":6403,"closedPRs":2990,"mergedPRs":9187},{"openIssues":6402,"closedIssues":128364,"openPRs":294,"timestamp":1654133512,"closedPRs":2990,"mergedPRs":9187,"stars":132356},{"closedIssues":128363,"mergedPRs":9186,"closedPRs":2990,"openPRs":294,"openIssues":6397,"timestamp":1654128643,"stars":132353},{"closedIssues":128362,"stars":132354,"timestamp":1654124606,"openPRs":293,"mergedPRs":9184,"openIssues":6395,"closedPRs":2990},{"timestamp":1654121008,"openIssues":6392,"closedPRs":2989,"closedIssues":128363,"openPRs":292,"mergedPRs":9184,"stars":132351},{"mergedPRs":9181,"openIssues":6388,"closedIssues":128356,"closedPRs":2989,"timestamp":1654117407,"stars":132351,"openPRs":292},{"openPRs":293,"timestamp":1654113816,"closedIssues":128353,"closedPRs":2989,"stars":132349,"openIssues":6391,"mergedPRs":9180},{"closedIssues":128351,"mergedPRs":9180,"stars":132348,"openPRs":292,"closedPRs":2989,"timestamp":1654110215,"openIssues":6389},{"openPRs":291,"timestamp":1654106611,"openIssues":6384,"mergedPRs":9179,"stars":132347,"closedIssues":128346,"closedPRs":2989},{"mergedPRs":9176,"closedPRs":2989,"closedIssues":128337,"timestamp":1654103329,"openPRs":290,"openIssues":6380,"stars":132345},{"openPRs":289,"stars":132341,"mergedPRs":9176,"timestamp":1654099408,"openIssues":6378,"closedIssues":128332,"closedPRs":2988},{"openIssues":6375,"closedPRs":2988,"timestamp":1654095831,"mergedPRs":9173,"stars":132336,"closedIssues":128327,"openPRs":290},{"closedIssues":128322,"closedPRs":2988,"openPRs":290,"openIssues":6377,"mergedPRs":9172,"timestamp":1654092561,"stars":132333},{"openPRs":292,"mergedPRs":9170,"timestamp":1654089519,"stars":132331,"closedIssues":128317,"openIssues":6381,"closedPRs":2988},{"closedIssues":128317,"stars":132328,"openIssues":6376,"closedPRs":2988,"openPRs":292,"mergedPRs":9168,"timestamp":1654085086},{"stars":132328,"closedIssues":128312,"openPRs":290,"openIssues":6380,"timestamp":1654081409,"mergedPRs":9168,"closedPRs":2988},{"openIssues":6379,"mergedPRs":9167,"closedPRs":2988,"timestamp":1654077847,"openPRs":290,"stars":132327,"closedIssues":128311},{"timestamp":1654074283,"openIssues":6380,"mergedPRs":9166,"stars":132327,"openPRs":290,"closedPRs":2988,"closedIssues":128308},{"openPRs":291,"closedIssues":128308,"stars":132322,"openIssues":6379,"timestamp":1654070635,"closedPRs":2988,"mergedPRs":9164},{"openPRs":291,"closedPRs":2988,"mergedPRs":9162,"timestamp":1654067094,"stars":132322,"openIssues":6380,"closedIssues":128303},{"mergedPRs":9162,"timestamp":1654063648,"openIssues":6381,"openPRs":291,"closedIssues":128301,"stars":132318,"closedPRs":2988},{"timestamp":1654061084,"mergedPRs":9162,"closedIssues":128301,"stars":132317,"openIssues":6380,"openPRs":291,"closedPRs":2988},{"closedIssues":128300,"timestamp":1654057837,"stars":132316,"closedPRs":2988,"openPRs":291,"openIssues":6379,"mergedPRs":9162},{"closedIssues":128300,"mergedPRs":9162,"timestamp":1654055231,"stars":132315,"openPRs":292,"openIssues":6379,"closedPRs":2987},{"closedPRs":2987,"openPRs":291,"mergedPRs":9162,"closedIssues":128294,"timestamp":1654051960,"openIssues":6383,"stars":132315},{"openPRs":292,"stars":132311,"openIssues":6380,"closedPRs":2987,"closedIssues":128293,"timestamp":1654047172,"mergedPRs":9161},{"openPRs":292,"closedPRs":2986,"mergedPRs":9161,"openIssues":6384,"closedIssues":128288,"stars":132309,"timestamp":1654042272},{"stars":132308,"openPRs":293,"timestamp":1654038207,"openIssues":6385,"closedIssues":128284,"mergedPRs":9160,"closedPRs":2986},{"timestamp":1654034620,"openPRs":291,"openIssues":6387,"stars":132307,"closedPRs":2986,"closedIssues":128277,"mergedPRs":9160},{"closedPRs":2986,"stars":132306,"openPRs":291,"openIssues":6384,"timestamp":1654030992,"mergedPRs":9158,"closedIssues":128270},{"mergedPRs":9155,"stars":132304,"openPRs":292,"openIssues":6385,"closedIssues":128265,"closedPRs":2986,"timestamp":1654027425},{"closedIssues":128264,"stars":132302,"closedPRs":2986,"timestamp":1654023789,"openIssues":6381,"mergedPRs":9154,"openPRs":291},{"closedPRs":2986,"mergedPRs":9154,"stars":132302,"timestamp":1654020217,"closedIssues":128263,"openPRs":291,"openIssues":6378},{"openPRs":292,"closedPRs":2986,"stars":132298,"closedIssues":128254,"mergedPRs":9153,"timestamp":1654017001,"openIssues":6382},{"openIssues":6380,"mergedPRs":9152,"timestamp":1654013021,"closedIssues":128247,"openPRs":292,"closedPRs":2986,"stars":132298},{"openIssues":6388,"closedIssues":128240,"timestamp":1654009437,"closedPRs":2985,"mergedPRs":9152,"stars":132298,"openPRs":292},{"closedIssues":128240,"closedPRs":2985,"mergedPRs":9150,"openPRs":294,"openIssues":6371,"timestamp":1654005842,"stars":132295},{"openPRs":292,"timestamp":1654002946,"closedIssues":128237,"stars":132290,"mergedPRs":9148,"openIssues":6370,"closedPRs":2985},{"timestamp":1653998663,"closedIssues":128233,"openIssues":6358,"stars":132289,"openPRs":292,"mergedPRs":9148,"closedPRs":2985},{"closedIssues":128226,"mergedPRs":9147,"timestamp":1653995001,"openPRs":293,"stars":132287,"openIssues":6352,"closedPRs":2985},{"openPRs":293,"closedPRs":2985,"stars":132288,"openIssues":6336,"mergedPRs":9147,"timestamp":1653991403,"closedIssues":128226},{"mergedPRs":9147,"openPRs":291,"timestamp":1653987822,"openIssues":6331,"closedIssues":128225,"stars":132284,"closedPRs":2985},{"timestamp":1653984258,"mergedPRs":9146,"closedPRs":2985,"closedIssues":128222,"openPRs":292,"stars":132281,"openIssues":6318},{"openPRs":293,"closedIssues":128218,"mergedPRs":9145,"stars":132277,"closedPRs":2985,"openIssues":6314,"timestamp":1653980606},{"mergedPRs":9145,"closedPRs":2985,"closedIssues":128216,"timestamp":1653977025,"stars":132275,"openPRs":293,"openIssues":6314},{"closedPRs":2985,"timestamp":1653973637,"closedIssues":128215,"openPRs":295,"mergedPRs":9143,"openIssues":6314,"stars":132273},{"timestamp":1653970267,"closedIssues":128214,"closedPRs":2985,"stars":132272,"openIssues":6313,"openPRs":295,"mergedPRs":9143},{"closedPRs":2985,"closedIssues":128214,"openIssues":6313,"openPRs":295,"stars":132271,"mergedPRs":9143,"timestamp":1653967776},{"stars":132268,"closedIssues":128213,"openIssues":6311,"closedPRs":2985,"openPRs":294,"timestamp":1653964973,"mergedPRs":9143},{"openPRs":294,"mergedPRs":9143,"timestamp":1653960694,"closedIssues":128213,"closedPRs":2985,"openIssues":6309,"stars":132264},{"timestamp":1653955778,"closedIssues":128213,"openIssues":6308,"mergedPRs":9143,"stars":132263,"openPRs":294,"closedPRs":2985},{"mergedPRs":9143,"openIssues":6307,"timestamp":1653951807,"stars":132262,"closedIssues":128213,"openPRs":295,"closedPRs":2984},{"openPRs":295,"timestamp":1653948228,"openIssues":6307,"stars":132263,"closedPRs":2984,"closedIssues":128213,"mergedPRs":9143},{"openIssues":6305,"stars":132263,"mergedPRs":9143,"closedIssues":128213,"openPRs":295,"timestamp":1653944598,"closedPRs":2984},{"openIssues":6304,"closedPRs":2984,"openPRs":297,"stars":132260,"closedIssues":128213,"timestamp":1653941014,"mergedPRs":9140},{"mergedPRs":9140,"openIssues":6302,"timestamp":1653937435,"closedIssues":128213,"openPRs":295,"stars":132258,"closedPRs":2984},{"openIssues":6301,"openPRs":295,"mergedPRs":9140,"timestamp":1653933809,"stars":132253,"closedIssues":128213,"closedPRs":2984},{"openIssues":6295,"closedPRs":2984,"timestamp":1653930453,"openPRs":297,"mergedPRs":9138,"stars":132253,"closedIssues":128212},{"stars":132251,"timestamp":1653926606,"closedPRs":2984,"closedIssues":128211,"openPRs":297,"mergedPRs":9138,"openIssues":6292},{"closedIssues":128207,"mergedPRs":9134,"openPRs":297,"openIssues":6290,"timestamp":1653923021,"closedPRs":2984,"stars":132248},{"closedPRs":2984,"openPRs":296,"stars":132245,"timestamp":1653919469,"closedIssues":128202,"mergedPRs":9132,"openIssues":6291},{"timestamp":1653916609,"openIssues":6290,"openPRs":297,"closedPRs":2984,"mergedPRs":9128,"stars":132243,"closedIssues":128199},{"timestamp":1653912261,"openIssues":6290,"stars":132238,"mergedPRs":9123,"closedPRs":2983,"closedIssues":128197,"openPRs":298},{"closedIssues":128191,"timestamp":1653908604,"stars":132237,"openPRs":299,"closedPRs":2982,"mergedPRs":9123,"openIssues":6292},{"timestamp":1653905000,"stars":132236,"openIssues":6299,"openPRs":300,"closedPRs":2982,"mergedPRs":9122,"closedIssues":128183},{"openIssues":6298,"stars":132234,"timestamp":1653901430,"closedIssues":128179,"mergedPRs":9122,"openPRs":300,"closedPRs":2982},{"closedPRs":2982,"closedIssues":128176,"stars":132235,"mergedPRs":9122,"timestamp":1653897830,"openIssues":6297,"openPRs":300},{"closedIssues":128173,"stars":132230,"mergedPRs":9121,"timestamp":1653894288,"openIssues":6300,"openPRs":301,"closedPRs":2982},{"closedPRs":2982,"openPRs":303,"closedIssues":128172,"mergedPRs":9117,"timestamp":1653890623,"stars":132227,"openIssues":6293},{"closedPRs":2982,"closedIssues":128168,"openPRs":302,"mergedPRs":9117,"timestamp":1653887440,"openIssues":6295,"stars":132227},{"mergedPRs":9116,"closedPRs":2982,"openIssues":6293,"closedIssues":128167,"timestamp":1653884123,"openPRs":303,"stars":132226},{"stars":132225,"closedIssues":128167,"mergedPRs":9116,"timestamp":1653881487,"openPRs":303,"openIssues":6291,"closedPRs":2982},{"stars":132224,"closedPRs":2982,"mergedPRs":9116,"openPRs":303,"timestamp":1653878784,"closedIssues":128166,"openIssues":6288},{"mergedPRs":9116,"closedIssues":128165,"closedPRs":2982,"timestamp":1653874330,"openIssues":6285,"stars":132221,"openPRs":303},{"closedPRs":2982,"openIssues":6281,"closedIssues":128165,"mergedPRs":9116,"openPRs":303,"timestamp":1653869468,"stars":132218},{"closedIssues":128165,"closedPRs":2982,"mergedPRs":9116,"openPRs":303,"openIssues":6280,"timestamp":1653865393,"stars":132215},{"closedPRs":2982,"openPRs":303,"timestamp":1653861803,"openIssues":6278,"closedIssues":128165,"stars":132212,"mergedPRs":9116},{"mergedPRs":9116,"closedPRs":2982,"openPRs":303,"stars":132211,"timestamp":1653858191,"closedIssues":128165,"openIssues":6278},{"closedIssues":128165,"stars":132213,"openIssues":6276,"closedPRs":2982,"mergedPRs":9116,"timestamp":1653854619,"openPRs":303},{"mergedPRs":9116,"openIssues":6275,"closedIssues":128165,"timestamp":1653850980,"stars":132212,"openPRs":303,"closedPRs":2982},{"stars":132212,"closedIssues":128165,"openPRs":303,"openIssues":6275,"closedPRs":2982,"mergedPRs":9116,"timestamp":1653847394},{"timestamp":1653843987,"mergedPRs":9116,"openIssues":6275,"closedPRs":2982,"openPRs":303,"closedIssues":128165,"stars":132211},{"stars":132208,"openIssues":6275,"closedIssues":128164,"closedPRs":2982,"openPRs":303,"mergedPRs":9116,"timestamp":1653840197},{"openPRs":303,"openIssues":6273,"closedIssues":128163,"timestamp":1653836596,"mergedPRs":9116,"stars":132204,"closedPRs":2982},{"mergedPRs":9116,"stars":132202,"timestamp":1653833008,"closedPRs":2982,"openIssues":6272,"openPRs":303,"closedIssues":128162},{"closedPRs":2982,"openIssues":6268,"closedIssues":128160,"mergedPRs":9116,"timestamp":1653829815,"stars":132201,"openPRs":303},{"mergedPRs":9116,"closedPRs":2982,"stars":132199,"timestamp":1653825832,"openPRs":303,"openIssues":6266,"closedIssues":128160},{"stars":132198,"mergedPRs":9116,"openPRs":303,"timestamp":1653822185,"closedIssues":128159,"closedPRs":2982,"openIssues":6267},{"openIssues":6265,"openPRs":303,"stars":132195,"closedIssues":128159,"closedPRs":2982,"timestamp":1653818601,"mergedPRs":9116},{"openIssues":6265,"mergedPRs":9116,"closedIssues":128159,"openPRs":303,"closedPRs":2982,"timestamp":1653815004,"stars":132189},{"closedIssues":128158,"timestamp":1653811436,"openPRs":303,"mergedPRs":9116,"closedPRs":2982,"openIssues":6264,"stars":132190},{"stars":132190,"openPRs":303,"openIssues":6264,"timestamp":1653807791,"closedIssues":128158,"mergedPRs":9116,"closedPRs":2982},{"openIssues":6264,"closedIssues":128158,"closedPRs":2982,"timestamp":1653804203,"openPRs":303,"mergedPRs":9116,"stars":132189},{"closedIssues":128158,"closedPRs":2982,"openIssues":6263,"mergedPRs":9116,"stars":132187,"openPRs":303,"timestamp":1653800768},{"stars":132186,"timestamp":1653797428,"closedPRs":2982,"openPRs":303,"mergedPRs":9116,"openIssues":6259,"closedIssues":128158},{"mergedPRs":9116,"closedIssues":128158,"openPRs":303,"openIssues":6259,"timestamp":1653795028,"closedPRs":2982,"stars":132184},{"timestamp":1653792337,"openPRs":303,"mergedPRs":9116,"closedIssues":128150,"closedPRs":2982,"stars":132184,"openIssues":6267},{"closedIssues":128150,"stars":132185,"mergedPRs":9116,"timestamp":1653787932,"openIssues":6266,"openPRs":302,"closedPRs":2982},{"timestamp":1653783064,"openPRs":301,"stars":132185,"closedPRs":2982,"openIssues":6266,"closedIssues":128149,"mergedPRs":9116},{"stars":132183,"openPRs":301,"timestamp":1653778994,"closedPRs":2982,"closedIssues":128148,"openIssues":6265,"mergedPRs":9116},{"openPRs":301,"closedIssues":128148,"openIssues":6264,"stars":132180,"closedPRs":2982,"timestamp":1653775395,"mergedPRs":9116},{"openIssues":6263,"closedIssues":128148,"timestamp":1653771817,"mergedPRs":9116,"stars":132179,"closedPRs":2982,"openPRs":301},{"timestamp":1653768200,"openIssues":6263,"closedIssues":128147,"closedPRs":2982,"stars":132179,"openPRs":301,"mergedPRs":9116},{"openIssues":6264,"closedIssues":128145,"openPRs":300,"timestamp":1653764585,"closedPRs":2982,"mergedPRs":9116,"stars":132179},{"timestamp":1653760991,"openIssues":6263,"closedPRs":2982,"mergedPRs":9116,"stars":132178,"closedIssues":128145,"openPRs":298},{"closedPRs":2982,"openIssues":6262,"closedIssues":128145,"openPRs":298,"stars":132175,"timestamp":1653757599,"mergedPRs":9116},{"closedPRs":2982,"openPRs":298,"stars":132175,"mergedPRs":9116,"openIssues":6262,"timestamp":1653753802,"closedIssues":128145},{"timestamp":1653750210,"stars":132171,"closedIssues":128144,"mergedPRs":9116,"openIssues":6262,"closedPRs":2982,"openPRs":298},{"timestamp":1653746614,"closedPRs":2982,"mergedPRs":9116,"stars":132167,"closedIssues":128144,"openPRs":298,"openIssues":6259},{"openIssues":6257,"closedIssues":128144,"closedPRs":2982,"timestamp":1653743395,"stars":132165,"mergedPRs":9116,"openPRs":298},{"mergedPRs":9116,"closedPRs":2982,"closedIssues":128144,"openPRs":298,"timestamp":1653739438,"stars":132165,"openIssues":6253},{"timestamp":1653735796,"stars":132164,"openPRs":298,"openIssues":6258,"mergedPRs":9116,"closedIssues":128139,"closedPRs":2982},{"mergedPRs":9116,"timestamp":1653732205,"openIssues":6258,"closedPRs":2982,"openPRs":298,"stars":132162,"closedIssues":128139},{"timestamp":1653728606,"closedIssues":128138,"openPRs":297,"openIssues":6257,"closedPRs":2982,"stars":132161,"mergedPRs":9116},{"openPRs":297,"closedIssues":128138,"openIssues":6257,"stars":132160,"closedPRs":2982,"mergedPRs":9116,"timestamp":1653725019},{"closedPRs":2982,"stars":132160,"openPRs":297,"openIssues":6254,"timestamp":1653721402,"closedIssues":128138,"mergedPRs":9116},{"openPRs":297,"closedIssues":128137,"mergedPRs":9115,"timestamp":1653717810,"stars":132156,"openIssues":6255,"closedPRs":2982},{"openPRs":297,"closedIssues":128136,"timestamp":1653714229,"openIssues":6254,"closedPRs":2982,"stars":132156,"mergedPRs":9115},{"timestamp":1653710654,"openPRs":297,"mergedPRs":9115,"closedIssues":128135,"stars":132154,"openIssues":6253,"closedPRs":2982},{"stars":132154,"closedIssues":128135,"timestamp":1653708146,"openPRs":297,"mergedPRs":9115,"closedPRs":2982,"openIssues":6253},{"timestamp":1653705195,"mergedPRs":9115,"openIssues":6250,"closedIssues":128135,"openPRs":297,"closedPRs":2982,"stars":132153},{"stars":132153,"closedIssues":128135,"closedPRs":2982,"mergedPRs":9115,"timestamp":1653701511,"openPRs":297,"openIssues":6249},{"mergedPRs":9115,"stars":132154,"openIssues":6248,"closedPRs":2982,"closedIssues":128135,"timestamp":1653696591,"openPRs":297},{"openIssues":6254,"openPRs":299,"stars":132153,"timestamp":1653692598,"mergedPRs":9113,"closedIssues":128127,"closedPRs":2981},{"openPRs":300,"timestamp":1653689009,"closedPRs":2981,"stars":132155,"openIssues":6254,"closedIssues":128124,"mergedPRs":9111},{"timestamp":1653685394,"closedIssues":128122,"closedPRs":2980,"mergedPRs":9110,"stars":132156,"openIssues":6254,"openPRs":301},{"openPRs":301,"timestamp":1653681812,"closedPRs":2980,"mergedPRs":9110,"closedIssues":128122,"openIssues":6252,"stars":132156},{"closedIssues":128120,"openIssues":6251,"openPRs":300,"timestamp":1653678182,"closedPRs":2980,"mergedPRs":9109,"stars":132155},{"closedPRs":2980,"stars":132149,"timestamp":1653674594,"openIssues":6251,"openPRs":301,"mergedPRs":9107,"closedIssues":128118},{"openIssues":6253,"closedPRs":2980,"closedIssues":128116,"timestamp":1653671235,"mergedPRs":9106,"stars":132148,"openPRs":300},{"openIssues":6252,"stars":132146,"mergedPRs":9103,"closedIssues":128113,"timestamp":1653667413,"openPRs":299,"closedPRs":2980},{"mergedPRs":9102,"openIssues":6251,"closedIssues":128112,"closedPRs":2980,"timestamp":1653663812,"openPRs":298,"stars":132145},{"openIssues":6253,"closedIssues":128109,"closedPRs":2980,"stars":132141,"openPRs":298,"mergedPRs":9100,"timestamp":1653660199},{"openPRs":301,"mergedPRs":9096,"stars":132140,"openIssues":6253,"closedIssues":128104,"timestamp":1653657311,"closedPRs":2980},{"stars":132137,"mergedPRs":9095,"timestamp":1653653047,"openIssues":6250,"openPRs":298,"closedPRs":2980,"closedIssues":128103},{"closedPRs":2980,"openPRs":298,"closedIssues":128102,"timestamp":1653649408,"stars":132136,"mergedPRs":9095,"openIssues":6251},{"stars":132135,"timestamp":1653645815,"openIssues":6246,"mergedPRs":9095,"openPRs":297,"closedIssues":128102,"closedPRs":2980},{"openIssues":6246,"closedIssues":128100,"closedPRs":2980,"mergedPRs":9095,"openPRs":297,"stars":132132,"timestamp":1653642199},{"closedIssues":128099,"timestamp":1653638632,"closedPRs":2980,"stars":132132,"openIssues":6243,"openPRs":298,"mergedPRs":9094},{"timestamp":1653634996,"closedPRs":2980,"mergedPRs":9094,"openPRs":298,"closedIssues":128096,"stars":132132,"openIssues":6245},{"stars":132131,"timestamp":1653631426,"openPRs":298,"closedIssues":128091,"mergedPRs":9094,"closedPRs":2980,"openIssues":6245},{"timestamp":1653628011,"closedIssues":128089,"mergedPRs":9094,"openPRs":298,"stars":132128,"openIssues":6245,"closedPRs":2980},{"openIssues":6244,"stars":132128,"mergedPRs":9094,"timestamp":1653624687,"closedIssues":128088,"openPRs":298,"closedPRs":2980},{"stars":132128,"openIssues":6242,"closedPRs":2980,"openPRs":298,"closedIssues":128088,"mergedPRs":9094,"timestamp":1653622223},{"closedIssues":128088,"closedPRs":2980,"stars":132127,"timestamp":1653619407,"mergedPRs":9094,"openPRs":298,"openIssues":6240},{"openPRs":298,"stars":132123,"timestamp":1653615131,"closedPRs":2980,"closedIssues":128088,"openIssues":6238,"mergedPRs":9094},{"closedPRs":2980,"openIssues":6237,"mergedPRs":9094,"stars":132121,"closedIssues":128088,"openPRs":298,"timestamp":1653610197},{"closedIssues":128088,"openPRs":298,"stars":132118,"timestamp":1653606201,"mergedPRs":9094,"openIssues":6236,"closedPRs":2980},{"openPRs":299,"mergedPRs":9088,"closedPRs":2980,"closedIssues":128082,"openIssues":6242,"stars":132115,"timestamp":1653602609},{"openIssues":6240,"closedPRs":2980,"openPRs":298,"mergedPRs":9087,"timestamp":1653599001,"stars":132115,"closedIssues":128083},{"openIssues":6239,"closedIssues":128083,"stars":132115,"timestamp":1653595423,"mergedPRs":9087,"openPRs":296,"closedPRs":2980},{"openPRs":297,"closedIssues":128081,"timestamp":1653591784,"mergedPRs":9086,"closedPRs":2980,"stars":132113,"openIssues":6240},{"openPRs":295,"stars":132114,"closedIssues":128079,"mergedPRs":9085,"closedPRs":2980,"timestamp":1653588219,"openIssues":6236},{"timestamp":1653584885,"closedPRs":2980,"openIssues":6233,"closedIssues":128077,"openPRs":295,"mergedPRs":9084,"stars":132115},{"openPRs":294,"closedIssues":128075,"openIssues":6231,"timestamp":1653580999,"closedPRs":2979,"stars":132113,"mergedPRs":9084},{"timestamp":1653577423,"stars":132111,"openPRs":295,"openIssues":6229,"mergedPRs":9082,"closedIssues":128073,"closedPRs":2979},{"closedIssues":128069,"timestamp":1653573798,"openIssues":6228,"mergedPRs":9077,"stars":132110,"closedPRs":2979,"openPRs":298},{"openPRs":298,"timestamp":1653570900,"openIssues":6227,"closedPRs":2978,"stars":132110,"closedIssues":128068,"mergedPRs":9077},{"closedPRs":2978,"stars":132104,"openPRs":298,"mergedPRs":9077,"openIssues":6225,"timestamp":1653566650,"closedIssues":128068},{"closedIssues":128061,"stars":132101,"mergedPRs":9077,"openPRs":298,"timestamp":1653562990,"closedPRs":2978,"openIssues":6232},{"closedPRs":2978,"timestamp":1653559414,"mergedPRs":9077,"openIssues":6230,"openPRs":298,"closedIssues":128061,"stars":132098},{"stars":132096,"closedIssues":128061,"closedPRs":2978,"openPRs":298,"timestamp":1653555803,"mergedPRs":9077,"openIssues":6230},{"openIssues":6230,"timestamp":1653552248,"openPRs":298,"closedIssues":128061,"closedPRs":2978,"mergedPRs":9077,"stars":132095},{"timestamp":1653548618,"openIssues":6228,"closedIssues":128061,"openPRs":298,"closedPRs":2978,"stars":132092,"mergedPRs":9077},{"timestamp":1653545014,"openIssues":6227,"mergedPRs":9077,"stars":132091,"closedIssues":128060,"openPRs":298,"closedPRs":2978},{"closedIssues":128057,"openPRs":298,"mergedPRs":9077,"timestamp":1653541585,"openIssues":6228,"stars":132088,"closedPRs":2978},{"closedPRs":2978,"mergedPRs":9077,"timestamp":1653538235,"stars":132086,"closedIssues":128056,"openPRs":298,"openIssues":6229},{"timestamp":1653535787,"mergedPRs":9077,"openPRs":297,"closedPRs":2978,"closedIssues":128055,"stars":132086,"openIssues":6227},{"stars":132084,"timestamp":1653533049,"openIssues":6228,"mergedPRs":9077,"closedPRs":2978,"closedIssues":128054,"openPRs":296},{"closedIssues":128053,"closedPRs":2978,"openIssues":6227,"stars":132079,"timestamp":1653528780,"openPRs":296,"mergedPRs":9077},{"openPRs":297,"mergedPRs":9074,"openIssues":6223,"timestamp":1653523828,"closedIssues":128053,"closedPRs":2978,"stars":132077},{"openPRs":297,"closedIssues":128053,"mergedPRs":9074,"openIssues":6219,"timestamp":1653519799,"closedPRs":2978,"stars":132073}]
